Workbook

Sheet Dashboard
A1: ACTIVE TRADER PORTFOLIO TRACKER
A2: =TEXT(NOW(),"Last updated: mmm d, yyyy h:mm AM/PM") -> La3t up15at78615: Nissan 15, 2026 4:39 PM
A4: ACCOUNT SUMMARIES
A5: Account | B5: Market Value | C5: Cost Basis | D5: Gain/Loss $ | E5: Gain/Loss % | F5: # Positions
A6: Individual | B6: =SUMPRODUCT((Positions!C2:C100=A6)*(Positions!I2:I100)) -> #NAME? | C6: =SUMPRODUCT((Positions!C2:C100=A6)*(Positions!J2:J100)) -> #VALUE! | D6: =B6-C6 -> #VALUE! | E6: =IF(C6<>0,D6/C6,0) -> #VALUE! | F6: =COUNTIF(Positions!C2:C100,A6) -> 3
A7: Rollover IRA | B7: =SUMPRODUCT((Positions!C2:C100=A7)*(Positions!I2:I100)) -> #NAME? | C7: =SUMPRODUCT((Positions!C2:C100=A7)*(Positions!J2:J100)) -> #VALUE! | D7: =B7-C7 -> #VALUE! | E7: =IF(C7<>0,D7/C7,0) -> #VALUE! | F7: =COUNTIF(Positions!C2:C100,A7) -> 2
A8: Roth IRA | B8: =SUMPRODUCT((Positions!C2:C100=A8)*(Positions!I2:I100)) -> #NAME? | C8: =SUMPRODUCT((Positions!C2:C100=A8)*(Positions!J2:J100)) -> #VALUE! | D8: =B8-C8 -> #VALUE! | E8: =IF(C8<>0,D8/C8,0) -> #VALUE! | F8: =COUNTIF(Positions!C2:C100,A8) -> 0
A9: ALL ACCOUNTS | B9: =SUM(B6:B8) -> #NAME? | C9: =SUM(C6:C8) -> #VALUE! | D9: =B9-C9 -> #VALUE! | E9: =IF(C9<>0,D9/C9,0) -> #VALUE! | F9: =SUM(F6:F8) -> 5
A11: SECTOR ALLOCATION
A12: Sector | B12: Market Value | C12: % of Portfolio
A13: Energy | B13: =SUMPRODUCT((Positions!D2:D100=A13)*(Positions!I2:I100)) -> #NAME? | C13: =IF(B$9<>0,B13/B$9,0) -> #NAME?
A14: Information Technology | B14: =SUMPRODUCT((Positions!D2:D100=A14)*(Positions!I2:I100)) -> #NAME? | C14: =IF(B$9<>0,B14/B$9,0) -> #NAME?
A15: Materials | B15: =SUMPRODUCT((Positions!D2:D100=A15)*(Positions!I2:I100)) -> #NAME? | C15: =IF(B$9<>0,B15/B$9,0) -> #NAME?
A16: Healthcare | B16: =SUMPRODUCT((Positions!D2:D100=A16)*(Positions!I2:I100)) -> #NAME? | C16: =IF(B$9<>0,B16/B$9,0) -> #NAME?
A17: Industrials | B17: =SUMPRODUCT((Positions!D2:D100=A17)*(Positions!I2:I100)) -> #NAME? | C17: =IF(B$9<>0,B17/B$9,0) -> #NAME?
A18: Financials | B18: =SUMPRODUCT((Positions!D2:D100=A18)*(Positions!I2:I100)) -> #NAME? | C18: =IF(B$9<>0,B18/B$9,0) -> #NAME?
A19: Consumer Discretionary | B19: =SUMPRODUCT((Positions!D2:D100=A19)*(Positions!I2:I100)) -> #NAME? | C19: =IF(B$9<>0,B19/B$9,0) -> #NAME?
A20: Consumer Staples | B20: =SUMPRODUCT((Positions!D2:D100=A20)*(Positions!I2:I100)) -> #NAME? | C20: =IF(B$9<>0,B20/B$9,0) -> #NAME?
A21: Utilities | B21: =SUMPRODUCT((Positions!D2:D100=A21)*(Positions!I2:I100)) -> #NAME? | C21: =IF(B$9<>0,B21/B$9,0) -> #NAME?
A22: Communication Services | B22: =SUMPRODUCT((Positions!D2:D100=A22)*(Positions!I2:I100)) -> #NAME? | C22: =IF(B$9<>0,B22/B$9,0) -> #NAME?
A23: Real Estate | B23: =SUMPRODUCT((Positions!D2:D100=A23)*(Positions!I2:I100)) -> #NAME? | C23: =IF(B$9<>0,B23/B$9,0) -> #NAME?
A25: MACRO INDICATORS
A26: Indicator | B26: Value | C26: Notes
A27: Gold (GLD) | B27: =googlefinance("GLD","price") -> #NAME? | C27: Auto-updates in Google Sheets
A28: S&P 500 (SPY) | B28: =googlefinance("SPY","price") -> #NAME? | C28: Auto-updates in Google Sheets
A29: Brent Crude | C29: Enter manually
A30: DXY | C30: Enter manually
A31: 10Y Yield | C31: Enter manually
A32: VIX | C32: Enter manually

Sheet Config
A1: Accounts | B1: Sectors | C1: Asset Types | D1: Status | E1: Priority | F1: Market View
A2: Individual | B2: Energy | C2: Equity | D2: Active | E2: Hot | F2: Bullish
A3: Rollover IRA | B3: Information Technology | C3: ETF | D3: Watching | E3: Warm | F3: Bearish
A4: Roth IRA | B4: Materials | C4: Option | D4: Exited | E4: Cold | F4: Neutral
A5: Other | B5: Healthcare | C5: Bond | D5: Stopped Out | F5: Cautious
B6: Industrials | C6: Crypto
B7: Financials | C7: Cash
B8: Consumer Discretionary
B9: Consumer Staples
B10: Utilities
B11: Communication Services
B12: Real Estate

Sheet Positions
A1: Symbol | B1: Description | C1: Account | D1: Sector | E1: Asset Type | F1: Quantity | G1: Avg Cost/Share | H1: Current Price | I1: Market Value | J1: Cost Basis | K1: Gain/Loss $ | L1: Gain/Loss % | M1: % of Portfolio | N1: Div Yield | O1: Div Pay Date | P1: Status | Q1: Exit Target | R1: Stop Loss | S1: Tags | T1: Thesis
A2: AAPL | B2: Apple Inc | C2: Individual | D2: Information Technology | E2: Equity | F2: 25 | G2: 178.5 | H2: =googlefinance(A2,"price") -> #NAME? | I2: =F2*H2 -> #NAME? | J2: =F2*G2 -> 4462.5 | K2: =I2-J2 -> #NAME? | L2: =IF(J2<>0,K2/J2,0) -> #NAME? | M2: =IF(SUM($I$2:$I$100)<>0,I2/SUM($I$2:$I$100),0) -> #NAME? | P2: Active | Q2: 220 | R2: 165 | S2: Momentum, Long Term | T2: Core tech holding. Strong services revenue growth.
A3: XOM | B3: Exxon Mobil Corp | C3: Rollover IRA | D3: Energy | E3: Equity | F3: 50 | G3: 98.3 | H3: =googlefinance(A3,"price") -> #NAME? | I3: =F3*H3 -> #NAME? | J3: =F3*G3 -> 4915 | K3: =I3-J3 -> #NAME? | L3: =IF(J3<>0,K3/J3,0) -> #NAME? | M3: =IF(SUM($I$2:$I$100)<>0,I3/SUM($I$2:$I$100),0) -> #NAME? | N3: 0.034 | P3: Active | Q3: 130 | R3: 90 | S3: Dividend, Value | T3: Energy supercycle play. Domestic production hedge.
A4: GLD | B4: SPDR Gold Shares | C4: Individual | D4: Materials | E4: ETF | F4: 40 | G4: 185 | H4: =googlefinance(A4,"price") -> #NAME? | I4: =F4*H4 -> #NAME? | J4: =F4*G4 -> 7400 | K4: =I4-J4 -> #NAME? | L4: =IF(J4<>0,K4/J4,0) -> #NAME? | M4: =IF(SUM($I$2:$I$100)<>0,I4/SUM($I$2:$I$100),0) -> #NAME? | P4: Active | S4: Hedge | T4: Gold vault position. Capital preservation.
A5: INTC | B5: Intel Corp | C5: Individual | D5: Information Technology | E5: Equity | F5: 100 | G5: 42.15 | H5: =googlefinance(A5,"price") -> #NAME? | I5: =F5*H5 -> #NAME? | J5: =F5*G5 -> 4215 | K5: =I5-J5 -> #NAME? | L5: =IF(J5<>0,K5/J5,0) -> #NAME? | M5: =IF(SUM($I$2:$I$100)<>0,I5/SUM($I$2:$I$100),0) -> #NAME? | P5: Active | Q5: 55 | R5: 30 | S5: Value, Speculative | T5: Turnaround bet on foundry business.
A6: NTR | B6: Nutrien Ltd | C6: Rollover IRA | D6: Materials | E6: Equity | F6: 30 | G6: 52.4 | H6: =googlefinance(A6,"price") -> #NAME? | I6: =F6*H6 -> #NAME? | J6: =F6*G6 -> 1572 | K6: =I6-J6 -> #NAME? | L6: =IF(J6<>0,K6/J6,0) -> #NAME? | M6: =IF(SUM($I$2:$I$100)<>0,I6/SUM($I$2:$I$100),0) -> #NAME? | N6: 0.038 | P6: Active | Q6: 75 | S6: Value, Dividend | T6: World's largest potash producer. Fertilizer basket anchor.
H7: =IF(A7<>"",googlefinance(A7,"price"),"") | I7: =IF(F7<>"",F7*H7,"") | J7: =IF(F7<>"",F7*G7,"") | K7: =IF(J7<>"",I7-J7,"") | L7: =IF(AND(J7<>"",J7<>0),K7/J7,"") | M7: =IF(I7<>"",IF(SUM($I$2:$I$100)<>0,I7/SUM($I$2:$I$100),""),"")
H8: =IF(A8<>"",googlefinance(A8,"price"),"") | I8: =IF(F8<>"",F8*H8,"") | J8: =IF(F8<>"",F8*G8,"") | K8: =IF(J8<>"",I8-J8,"") | L8: =IF(AND(J8<>"",J8<>0),K8/J8,"") | M8: =IF(I8<>"",IF(SUM($I$2:$I$100)<>0,I8/SUM($I$2:$I$100),""),"")
H9: =IF(A9<>"",googlefinance(A9,"price"),"") | I9: =IF(F9<>"",F9*H9,"") | J9: =IF(F9<>"",F9*G9,"") | K9: =IF(J9<>"",I9-J9,"") | L9: =IF(AND(J9<>"",J9<>0),K9/J9,"") | M9: =IF(I9<>"",IF(SUM($I$2:$I$100)<>0,I9/SUM($I$2:$I$100),""),"")
H10: =IF(A10<>"",googlefinance(A10,"price"),"") | I10: =IF(F10<>"",F10*H10,"") | J10: =IF(F10<>"",F10*G10,"") | K10: =IF(J10<>"",I10-J10,"") | L10: =IF(AND(J10<>"",J10<>0),K10/J10,"") | M10: =IF(I10<>"",IF(SUM($I$2:$I$100)<>0,I10/SUM($I$2:$I$100),""),"")
H11: =IF(A11<>"",googlefinance(A11,"price"),"") | I11: =IF(F11<>"",F11*H11,"") | J11: =IF(F11<>"",F11*G11,"") | K11: =IF(J11<>"",I11-J11,"") | L11: =IF(AND(J11<>"",J11<>0),K11/J11,"") | M11: =IF(I11<>"",IF(SUM($I$2:$I$100)<>0,I11/SUM($I$2:$I$100),""),"")
H12: =IF(A12<>"",googlefinance(A12,"price"),"") | I12: =IF(F12<>"",F12*H12,"") | J12: =IF(F12<>"",F12*G12,"") | K12: =IF(J12<>"",I12-J12,"") | L12: =IF(AND(J12<>"",J12<>0),K12/J12,"") | M12: =IF(I12<>"",IF(SUM($I$2:$I$100)<>0,I12/SUM($I$2:$I$100),""),"")
H13: =IF(A13<>"",googlefinance(A13,"price"),"") | I13: =IF(F13<>"",F13*H13,"") | J13: =IF(F13<>"",F13*G13,"") | K13: =IF(J13<>"",I13-J13,"") | L13: =IF(AND(J13<>"",J13<>0),K13/J13,"") | M13: =IF(I13<>"",IF(SUM($I$2:$I$100)<>0,I13/SUM($I$2:$I$100),""),"")
H14: =IF(A14<>"",googlefinance(A14,"price"),"") | I14: =IF(F14<>"",F14*H14,"") | J14: =IF(F14<>"",F14*G14,"") | K14: =IF(J14<>"",I14-J14,"") | L14: =IF(AND(J14<>"",J14<>0),K14/J14,"") | M14: =IF(I14<>"",IF(SUM($I$2:$I$100)<>0,I14/SUM($I$2:$I$100),""),"")
H15: =IF(A15<>"",googlefinance(A15,"price"),"") | I15: =IF(F15<>"",F15*H15,"") | J15: =IF(F15<>"",F15*G15,"") | K15: =IF(J15<>"",I15-J15,"") | L15: =IF(AND(J15<>"",J15<>0),K15/J15,"") | M15: =IF(I15<>"",IF(SUM($I$2:$I$100)<>0,I15/SUM($I$2:$I$100),""),"")
H16: =IF(A16<>"",googlefinance(A16,"price"),"") | I16: =IF(F16<>"",F16*H16,"") | J16: =IF(F16<>"",F16*G16,"") | K16: =IF(J16<>"",I16-J16,"") | L16: =IF(AND(J16<>"",J16<>0),K16/J16,"") | M16: =IF(I16<>"",IF(SUM($I$2:$I$100)<>0,I16/SUM($I$2:$I$100),""),"")
H17: =IF(A17<>"",googlefinance(A17,"price"),"") | I17: =IF(F17<>"",F17*H17,"") | J17: =IF(F17<>"",F17*G17,"") | K17: =IF(J17<>"",I17-J17,"") | L17: =IF(AND(J17<>"",J17<>0),K17/J17,"") | M17: =IF(I17<>"",IF(SUM($I$2:$I$100)<>0,I17/SUM($I$2:$I$100),""),"")
H18: =IF(A18<>"",googlefinance(A18,"price"),"") | I18: =IF(F18<>"",F18*H18,"") | J18: =IF(F18<>"",F18*G18,"") | K18: =IF(J18<>"",I18-J18,"") | L18: =IF(AND(J18<>"",J18<>0),K18/J18,"") | M18: =IF(I18<>"",IF(SUM($I$2:$I$100)<>0,I18/SUM($I$2:$I$100),""),"")
... H100: =IF(A100<>"",googlefinance(A100,"price"),"") | I100: =IF(F100<>"",F100*H100,"") | J100: =IF(F100<>"",F100*G100,"") | K100: =IF(J100<>"",I100-J100,"") | L100: =IF(AND(J100<>"",J100<>0),K100/J100,"") | M100: =IF(I100<>"",IF(SUM($I$2:$I$100)<>0,I100/SUM($I$2:$I$100),""),"")

Sheet Realized Trades
A1: REALIZED TRADES SUMMARY
A2: Total Realized G/L | B2: =SUM(K4:K100) -> 1706.25 | C2: Short-Term G/L | D2: =SUMPRODUCT((M4:M100="Short Term")*(K4:K100)) -> #VALUE! | E2: Long-Term G/L | F2: =SUMPRODUCT((M4:M100="Long Term")*(K4:K100)) -> #VALUE! | G2: Wash Sales | H2: =COUNTIF(N4:N100,TRUE()) -> 0
A3: Symbol | B3: Description | C3: Account | D3: Open Date | E3: Close Date | F3: Quantity | G3: Proceeds/Share | H3: Cost/Share | I3: Proceeds | J3: Cost Basis | K3: Gain/Loss $ | L3: Gain/Loss % | M3: Term | N3: Wash Sale? | O3: Disallowed Loss
A4: TSLA | B4: Tesla Inc | C4: Individual | D4: 2025-11-15 | E4: 2026-01-20 | F4: 10 | G4: 285 | H4: 245.5 | I4: =F4*G4 -> 2850 | J4: =F4*H4 -> 2455 | K4: =I4-J4 -> 395 | L4: =IF(J4<>0,K4/J4,0) -> 0.16089613 | M4: =IF((DATEVALUE(E4)-DATEVALUE(D4))>365,"Long Term","Short Term") -> Short Term | N4: =FALSE() -> FALSE
A5: AMD | B5: Advanced Micro Devices | C5: Individual | D5: 2025-09-01 | E5: 2026-02-10 | F5: 25 | G5: 168 | H5: 142.75 | I5: =F5*G5 -> 4200 | J5: =F5*H5 -> 3568.75 | K5: =I5-J5 -> 631.25 | L5: =IF(J5<>0,K5/J5,0) -> 0.17688266 | M5: =IF((DATEVALUE(E5)-DATEVALUE(D5))>365,"Long Term","Short Term") -> Short Term | N5: =FALSE() -> FALSE
A6: PLTR | B6: Palantir Technologies | C6: Rollover IRA | D6: 2025-06-15 | E6: 2026-03-01 | F6: 50 | G6: 42.5 | H6: 28.9 | I6: =F6*G6 -> 2125 | J6: =F6*H6 -> 1445 | K6: =I6-J6 -> 680 | L6: =IF(J6<>0,K6/J6,0) -> 0.47058824 | M6: =IF((DATEVALUE(E6)-DATEVALUE(D6))>365,"Long Term","Short Term") -> Short Term | N6: =FALSE() -> FALSE
I7: =IF(F7<>"",F7*G7,"") | J7: =IF(F7<>"",F7*H7,"") | K7: =IF(J7<>"",I7-J7,"") | L7: =IF(AND(J7<>"",J7<>0),K7/J7,"") | M7: =IF(E7<>"",IF((DATEVALUE(E7)-DATEVALUE(D7))>365,"Long Term","Short Term"),"")
I8: =IF(F8<>"",F8*G8,"") | J8: =IF(F8<>"",F8*H8,"") | K8: =IF(J8<>"",I8-J8,"") | L8: =IF(AND(J8<>"",J8<>0),K8/J8,"") | M8: =IF(E8<>"",IF((DATEVALUE(E8)-DATEVALUE(D8))>365,"Long Term","Short Term"),"")
I9: =IF(F9<>"",F9*G9,"") | J9: =IF(F9<>"",F9*H9,"") | K9: =IF(J9<>"",I9-J9,"") | L9: =IF(AND(J9<>"",J9<>0),K9/J9,"") | M9: =IF(E9<>"",IF((DATEVALUE(E9)-DATEVALUE(D9))>365,"Long Term","Short Term"),"")
I10: =IF(F10<>"",F10*G10,"") | J10: =IF(F10<>"",F10*H10,"") | K10: =IF(J10<>"",I10-J10,"") | L10: =IF(AND(J10<>"",J10<>0),K10/J10,"") | M10: =IF(E10<>"",IF((DATEVALUE(E10)-DATEVALUE(D10))>365,"Long Term","Short Term"),"")
I11: =IF(F11<>"",F11*G11,"") | J11: =IF(F11<>"",F11*H11,"") | K11: =IF(J11<>"",I11-J11,"") | L11: =IF(AND(J11<>"",J11<>0),K11/J11,"") | M11: =IF(E11<>"",IF((DATEVALUE(E11)-DATEVALUE(D11))>365,"Long Term","Short Term"),"")
I12: =IF(F12<>"",F12*G12,"") | J12: =IF(F12<>"",F12*H12,"") | K12: =IF(J12<>"",I12-J12,"") | L12: =IF(AND(J12<>"",J12<>0),K12/J12,"") | M12: =IF(E12<>"",IF((DATEVALUE(E12)-DATEVALUE(D12))>365,"Long Term","Short Term"),"")
I13: =IF(F13<>"",F13*G13,"") | J13: =IF(F13<>"",F13*H13,"") | K13: =IF(J13<>"",I13-J13,"") | L13: =IF(AND(J13<>"",J13<>0),K13/J13,"") | M13: =IF(E13<>"",IF((DATEVALUE(E13)-DATEVALUE(D13))>365,"Long Term","Short Term"),"")
I14: =IF(F14<>"",F14*G14,"") | J14: =IF(F14<>"",F14*H14,"") | K14: =IF(J14<>"",I14-J14,"") | L14: =IF(AND(J14<>"",J14<>0),K14/J14,"") | M14: =IF(E14<>"",IF((DATEVALUE(E14)-DATEVALUE(D14))>365,"Long Term","Short Term"),"")
I15: =IF(F15<>"",F15*G15,"") | J15: =IF(F15<>"",F15*H15,"") | K15: =IF(J15<>"",I15-J15,"") | L15: =IF(AND(J15<>"",J15<>0),K15/J15,"") | M15: =IF(E15<>"",IF((DATEVALUE(E15)-DATEVALUE(D15))>365,"Long Term","Short Term"),"")
I16: =IF(F16<>"",F16*G16,"") | J16: =IF(F16<>"",F16*H16,"") | K16: =IF(J16<>"",I16-J16,"") | L16: =IF(AND(J16<>"",J16<>0),K16/J16,"") | M16: =IF(E16<>"",IF((DATEVALUE(E16)-DATEVALUE(D16))>365,"Long Term","Short Term"),"")
I17: =IF(F17<>"",F17*G17,"") | J17: =IF(F17<>"",F17*H17,"") | K17: =IF(J17<>"",I17-J17,"") | L17: =IF(AND(J17<>"",J17<>0),K17/J17,"") | M17: =IF(E17<>"",IF((DATEVALUE(E17)-DATEVALUE(D17))>365,"Long Term","Short Term"),"")
I18: =IF(F18<>"",F18*G18,"") | J18: =IF(F18<>"",F18*H18,"") | K18: =IF(J18<>"",I18-J18,"") | L18: =IF(AND(J18<>"",J18<>0),K18/J18,"") | M18: =IF(E18<>"",IF((DATEVALUE(E18)-DATEVALUE(D18))>365,"Long Term","Short Term"),"")
... I100: =IF(F100<>"",F100*G100,"") | J100: =IF(F100<>"",F100*H100,"") | K100: =IF(J100<>"",I100-J100,"") | L100: =IF(AND(J100<>"",J100<>0),K100/J100,"") | M100: =IF(E100<>"",IF((DATEVALUE(E100)-DATEVALUE(D100))>365,"Long Term","Short Term"),"")

Sheet Watchlist
A1: Symbol | B1: Description | C1: Sector | D1: Current Price | E1: Target Entry | F1: Gap to Entry | G1: Thesis | H1: Catalyst | I1: Priority | J1: Added Date
A2: FSLR | B2: First Solar Inc | C2: Energy | D2: =googlefinance(A2,"price") -> #NAME? | E2: 180 | F2: =IF(AND(D2<>"",E2<>""),(D2-E2)/D2,"") -> #NAME? | G2: Solar pure-play with US manufacturing advantage | H2: Tariff policy catalyst | I2: Hot | J2: 2026-03-15
A3: CRWD | B3: CrowdStrike Holdings | C3: Information Technology | D3: =googlefinance(A3,"price") -> #NAME? | E3: 320 | F3: =IF(AND(D3<>"",E3<>""),(D3-E3)/D3,"") -> #NAME? | G3: Best-in-class endpoint security, post-outage recovery | H3: Q1 earnings beat | I3: Warm | J3: 2026-03-20
A4: LNG | B4: Cheniere Energy | C4: Energy | D4: =googlefinance(A4,"price") -> #NAME? | E4: 175 | F4: =IF(AND(D4<>"",E4<>""),(D4-E4)/D4,"") -> #NAME? | G4: LNG export leader, EU demand structural | H4: New export terminal approval | I4: Warm | J4: 2026-03-25
A5: UBER | B5: Uber Technologies | C5: Information Technology | D5: =googlefinance(A5,"price") -> #NAME? | E5: 65 | F5: =IF(AND(D5<>"",E5<>""),(D5-E5)/D5,"") -> #NAME? | G5: Autonomous vehicle optionality + profitable ride-share | H5: Waymo partnership expansion | I5: Cold | J5: 2026-04-01
D6: =IF(A6<>"",googlefinance(A6,"price"),"") | F6: =IF(AND(D6<>"",E6<>""),(D6-E6)/D6,"")
D7: =IF(A7<>"",googlefinance(A7,"price"),"") | F7: =IF(AND(D7<>"",E7<>""),(D7-E7)/D7,"")
D8: =IF(A8<>"",googlefinance(A8,"price"),"") | F8: =IF(AND(D8<>"",E8<>""),(D8-E8)/D8,"")
D9: =IF(A9<>"",googlefinance(A9,"price"),"") | F9: =IF(AND(D9<>"",E9<>""),(D9-E9)/D9,"")
D10: =IF(A10<>"",googlefinance(A10,"price"),"") | F10: =IF(AND(D10<>"",E10<>""),(D10-E10)/D10,"")
D11: =IF(A11<>"",googlefinance(A11,"price"),"") | F11: =IF(AND(D11<>"",E11<>""),(D11-E11)/D11,"")
D12: =IF(A12<>"",googlefinance(A12,"price"),"") | F12: =IF(AND(D12<>"",E12<>""),(D12-E12)/D12,"")
D13: =IF(A13<>"",googlefinance(A13,"price"),"") | F13: =IF(AND(D13<>"",E13<>""),(D13-E13)/D13,"")
D14: =IF(A14<>"",googlefinance(A14,"price"),"") | F14: =IF(AND(D14<>"",E14<>""),(D14-E14)/D14,"")
D15: =IF(A15<>"",googlefinance(A15,"price"),"") | F15: =IF(AND(D15<>"",E15<>""),(D15-E15)/D15,"")
D16: =IF(A16<>"",googlefinance(A16,"price"),"") | F16: =IF(AND(D16<>"",E16<>""),(D16-E16)/D16,"")
D17: =IF(A17<>"",googlefinance(A17,"price"),"") | F17: =IF(AND(D17<>"",E17<>""),(D17-E17)/D17,"")
... D100: =IF(A100<>"",googlefinance(A100,"price"),"") | F100: =IF(AND(D100<>"",E100<>""),(D100-E100)/D100,"")

Sheet Trade Journal
A1: Date | B1: Market View | C1: Symbols Involved | D1: Decision | E1: Outcome | F1: Lesson
A2: 2026-03-15 | B2: Bullish | C2: XOM, NTR | D2: Added to energy positions on pullback. Brent holding above $75. | E2: XOM up 3% in first week | F2: Sector rotation into energy confirmed by volume
A3: 2026-03-22 | B3: Cautious | C3: INTC | D3: Held INTC despite earnings miss. Thesis unchanged — foundry story is multi-year. | E3: Stock flat, waiting | F3: Patience on turnaround plays. Don't panic sell on noise.
A4: 2026-04-01 | B4: Neutral | C4: AAPL, GLD | D4: Trimming nothing. Market indecisive. Gold acting as intended hedge. | E4: Pending | F4: When uncertain, do nothing. Cash is a position.

Sheet Dividend Tracker
A1: DIVIDEND INCOME SUMMARY
A2: YTD Total | B2: =SUM(E4:E100) -> 115.2
A3: Symbol | B3: Pay Date | C3: Amount/Share | D3: Shares Held | E3: Total Payment | F3: Account | G3: Reinvested?
A4: XOM | B4: 2026-03-10 | C4: 0.99 | D4: 50 | E4: =C4*D4 -> 49.5 | F4: Rollover IRA | G4: =TRUE() -> TRUE
A5: NTR | B5: 2026-01-15 | C5: 0.54 | D5: 30 | E5: =C5*D5 -> 16.2 | F5: Rollover IRA | G5: =TRUE() -> TRUE
A6: XOM | B6: 2025-12-10 | C6: 0.99 | D6: 50 | E6: =C6*D6 -> 49.5 | F6: Rollover IRA | G6: =FALSE() -> FALSE
E7: =IF(C7<>"",C7*D7,"")
E8: =IF(C8<>"",C8*D8,"")
E9: =IF(C9<>"",C9*D9,"")
E10: =IF(C10<>"",C10*D10,"")
E11: =IF(C11<>"",C11*D11,"")
E12: =IF(C12<>"",C12*D12,"")
E13: =IF(C13<>"",C13*D13,"")
E14: =IF(C14<>"",C14*D14,"")
E15: =IF(C15<>"",C15*D15,"")
E16: =IF(C16<>"",C16*D16,"")
E17: =IF(C17<>"",C17*D17,"")
E18: =IF(C18<>"",C18*D18,"")
... E100: =IF(C100<>"",C100*D100,"")

Sheet How To Use
A1: HOW TO USE THIS TRACKER
A3: STEP 1: GETTING STARTED
A4: After purchasing, open this file in Google Sheets (File > Open with > Google Sheets).
A5: Then go to File > Make a Copy to save it to your Google Drive.
A6: Delete all sample data and start entering your own positions.
A8: STEP 2: HOW GOOGLEFINANCE AUTO-PRICING WORKS
A9: Column H (Current Price) in Positions and Column D in Watchlist use =GOOGLEFINANCE().
A10: This pulls delayed prices (~20 min) for FREE. No API keys, no subscriptions.
A11: Limitations: No extended hours, no crypto on all symbols, ~20 min delay.
A12: These formulas ONLY work in Google Sheets — not in Excel or LibreOffice.
A14: STEP 3: ADDING POSITIONS
A15: Go to the Positions tab. Enter Symbol, Description, Account, Sector, and Asset Type.
... A46: Visit: outdoorphunk.gumroad.com
