Workbook

Sheet Dashboard
A1: ACTIVE TRADER PORTFOLIO TRACKER
A2: =TEXT(NOW(),"Last updated: mmm d, yyyy h:mm AM/PM") -> La3t up3at20263: Apr 3, 2026 10:28 PM
A4: ACCOUNT SUMMARY
A5: Account | B5: Market Value | C5: Cost Basis | D5: Gain/Loss $ | E5: Gain/Loss % | F5: # Positions
A6: Individual | B6: =SUMIFS(Positions!I:I,Positions!C:C,"Individual") -> 37087.2 | C6: =SUMIFS(Positions!J:J,Positions!C:C,"Individual") -> 24303.6 | D6: =B6-C6 -> 12783.6 | E6: =IF(C6<>0,D6/C6,0) -> 0.52599615 | F6: =COUNTIFS(Positions!C:C,"Individual") -> 6
A7: Rollover IRA | B7: =SUMIFS(Positions!I:I,Positions!C:C,"Rollover IRA") -> 10298.6 | C7: =SUMIFS(Positions!J:J,Positions!C:C,"Rollover IRA") -> 6487 | D7: =B7-C7 -> 3811.6 | E7: =IF(C7<>0,D7/C7,0) -> 0.58757515 | F7: =COUNTIFS(Positions!C:C,"Rollover IRA") -> 2
A8: ALL ACCOUNTS | B8: =SUM(Positions!I:I) -> 47385.8 | C8: =SUM(Positions!J:J) -> 30790.6 | D8: =B8-C8 -> 16595.2 | E8: =IF(C8<>0,D8/C8,0) -> 0.53896969 | F8: =COUNTA(Positions!A2:A200) -> 8
A10: SECTOR ALLOCATION
A11: Sector | B11: Market Value | C11: % of Portfolio
A12: Energy | B12: =SUMIFS(Positions!I:I,Positions!D:D,"Energy") -> 10494.5 | C12: =IF(SUM(Positions!I:I)<>0,B12/SUM(Positions!I:I),0) -> 0.2214693
A13: IT | B13: =SUMIFS(Positions!I:I,Positions!D:D,"IT") -> 11436 | C13: =IF(SUM(Positions!I:I)<>0,B13/SUM(Positions!I:I),0) -> 0.24133812
A14: Materials | B14: =SUMIFS(Positions!I:I,Positions!D:D,"Materials") -> 20740.2 | C14: =IF(SUM(Positions!I:I)<>0,B14/SUM(Positions!I:I),0) -> 0.43768808
A15: Healthcare | B15: =SUMIFS(Positions!I:I,Positions!D:D,"Healthcare") -> 0 | C15: =IF(SUM(Positions!I:I)<>0,B15/SUM(Positions!I:I),0) -> 0
A16: Industrials | B16: =SUMIFS(Positions!I:I,Positions!D:D,"Industrials") -> 4715.1 | C16: =IF(SUM(Positions!I:I)<>0,B16/SUM(Positions!I:I),0) -> 0.099504493
A17: Financials | B17: =SUMIFS(Positions!I:I,Positions!D:D,"Financials") -> 0 | C17: =IF(SUM(Positions!I:I)<>0,B17/SUM(Positions!I:I),0) -> 0
A18: Consumer | B18: =SUMIFS(Positions!I:I,Positions!D:D,"Consumer") -> 0 | C18: =IF(SUM(Positions!I:I)<>0,B18/SUM(Positions!I:I),0) -> 0
A19: Utilities | B19: =SUMIFS(Positions!I:I,Positions!D:D,"Utilities") -> 0 | C19: =IF(SUM(Positions!I:I)<>0,B19/SUM(Positions!I:I),0) -> 0
A20: Comm Services | B20: =SUMIFS(Positions!I:I,Positions!D:D,"Comm Services") -> 0 | C20: =IF(SUM(Positions!I:I)<>0,B20/SUM(Positions!I:I),0) -> 0
A21: Real Estate | B21: =SUMIFS(Positions!I:I,Positions!D:D,"Real Estate") -> 0 | C21: =IF(SUM(Positions!I:I)<>0,B21/SUM(Positions!I:I),0) -> 0
A23: MACRO INDICATORS
A24: Indicator | B24: Value | C24: Trend | D24: Notes
A25: Brent Crude
A26: Gold (oz) | B26: =IFERROR(__xludf.DUMMYFUNCTION("googlefinance(""GLD"",""price"")"),429.41) -> 429.41 | C26: Auto (GLD ETF)
A27: DXY
A28: 10Y Treasury
A29: VIX

Sheet Positions
A1: Symbol | B1: Description | C1: Account | D1: Sector | E1: Asset Type | F1: Quantity | G1: Avg Cost/Share | H1: Current Price | I1: Market Value | J1: Cost Basis | K1: Gain/Loss $ | L1: Gain/Loss % | M1: % of Portfolio | N1: Div Yield | O1: Div Pay Date | P1: Status | Q1: Exit Target | R1: Stop Loss | S1: Tags | T1: Thesis
A2: AAPL | B2: Apple Inc | C2: Individual | D2: IT | E2: Equity | F2: 25 | G2: 178.5 | H2: =IFERROR(__xludf.DUMMYFUNCTION("googlefinance(A2,""price"")"),255.92) -> 255.92 | I2: =F2*H2 -> 6398 | J2: =F2*G2 -> 4462.5 | K2: =I2-J2 -> 1935.5 | L2: =IF(J2<>0,K2/J2,0) -> 0.43372549 | M2: =IF(SUM($I$2:$I$200)<>0,I2/SUM($I$2:$I$200),0) -> 0.13501935 | N2: 0.005 | P2: Active | Q2: 220 | R2: 165 | S2: Momentum, Long Term | T2: Core tech holding. Strong services revenue growth.
A3: XOM | B3: Exxon Mobil Corp | C3: Rollover IRA | D3: Energy | E3: Equity | F3: 50 | G3: 98.3 | H3: =IFERROR(__xludf.DUMMYFUNCTION("googlefinance(A3,""price"")"),160.69) -> 160.69 | I3: =F3*H3 -> 8034.5 | J3: =F3*G3 -> 4915 | K3: =I3-J3 -> 3119.5 | L3: =IF(J3<>0,K3/J3,0) -> 0.63468973 | M3: =IF(SUM($I$2:$I$200)<>0,I3/SUM($I$2:$I$200),0) -> 0.16955501 | N3: 0.034 | P3: Active | Q3: 130 | R3: 90 | S3: Dividend, Value | T3: Energy supercycle play. Domestic production hedge.
A4: GLD | B4: SPDR Gold Shares | C4: Individual | D4: Materials | E4: ETF | F4: 40 | G4: 185 | H4: =IFERROR(__xludf.DUMMYFUNCTION("googlefinance(A4,""price"")"),429.41) -> 429.41 | I4: =F4*H4 -> 17176.4 | J4: =F4*G4 -> 7400 | K4: =I4-J4 -> 9776.4 | L4: =IF(J4<>0,K4/J4,0) -> 1.3211351 | M4: =IF(SUM($I$2:$I$200)<>0,I4/SUM($I$2:$I$200),0) -> 0.3624799 | N4: 0 | P4: Active | S4: Hedge | T4: Gold vault position. Capital preservation.
A5: INTC | B5: Intel Corp | C5: Individual | D5: IT | E5: Equity | F5: 100 | G5: 42.15 | H5: =IFERROR(__xludf.DUMMYFUNCTION("googlefinance(A5,""price"")"),50.38) -> 50.38 | I5: =F5*H5 -> 5038 | J5: =F5*G5 -> 4215 | K5: =I5-J5 -> 823 | L5: =IF(J5<>0,K5/J5,0) -> 0.19525504 | M5: =IF(SUM($I$2:$I$200)<>0,I5/SUM($I$2:$I$200),0) -> 0.10631877 | N5: 0.015 | P5: Active | Q5: 55 | R5: 30 | S5: Value, Speculative | T5: Turnaround bet on foundry business.
A6: NTR | B6: Nutrien Ltd | C6: Rollover IRA | D6: Materials | E6: Equity | F6: 30 | G6: 52.4 | H6: =IFERROR(__xludf.DUMMYFUNCTION("googlefinance(A6,""price"")"),75.47) -> 75.47 | I6: =F6*H6 -> 2264.1 | J6: =F6*G6 -> 1572 | K6: =I6-J6 -> 692.1 | L6: =IF(J6<>0,K6/J6,0) -> 0.44026718 | M6: =IF(SUM($I$2:$I$200)<>0,I6/SUM($I$2:$I$200),0) -> 0.047780137 | N6: 0.038 | P6: Active | Q6: 75 | S6: Value, Dividend | T6: Worlds largest potash producer. Fertilizer anchor.
A7: NAT | B7: Nordic American Tanker | C7: Individual | D7: Energy | E7: Equity | F7: 400 | G7: 5.92 | H7: =IFERROR(__xludf.DUMMYFUNCTION("googlefinance(A7,""price"")"),6.15) -> 6.15 | I7: =F7*H7 -> 2460 | J7: =F7*G7 -> 2368 | K7: =I7-J7 -> 92 | L7: =IF(J7<>0,K7/J7,0) -> 0.038851351 | M7: =IF(SUM($I$2:$I$200)<>0,I7/SUM($I$2:$I$200),0) -> 0.051914287 | N7: 0.116 | P7: Active | Q7: 8 | R7: 5.5 | S7: Dividend, Value | T7: Tanker play. Longer voyages = more revenue.
A8: CF | B8: CF Industries | C8: Individual | D8: Materials | E8: Equity | F8: 10 | G8: 131.07 | H8: =IFERROR(__xludf.DUMMYFUNCTION("googlefinance(A8,""price"")"),129.97) -> 129.97 | I8: =F8*H8 -> 1299.7 | J8: =F8*G8 -> 1310.7 | K8: =I8-J8 -> -11 | L8: =IF(J8<>0,K8/J8,0) -> -0.008392462 | M8: =IF(SUM($I$2:$I$200)<>0,I8/SUM($I$2:$I$200),0) -> 0.027428048 | N8: 0.015 | P8: Active | Q8: 150 | R8: 124 | S8: Value | T8: US nitrogen producer. Cheapest nat gas input costs.
A9: GNK | B9: Genco Shipping | C9: Individual | D9: Industrials | E9: Equity | F9: 195 | G9: 23.32 | H9: =IFERROR(__xludf.DUMMYFUNCTION("googlefinance(A9,""price"")"),24.18) -> 24.18 | I9: =F9*H9 -> 4715.1 | J9: =F9*G9 -> 4547.4 | K9: =I9-J9 -> 167.7 | L9: =IF(J9<>0,K9/J9,0) -> 0.036878216 | M9: =IF(SUM($I$2:$I$200)<>0,I9/SUM($I$2:$I$200),0) -> 0.099504493 | N9: 0.089 | P9: Active | Q9: 28 | R9: 22.51 | S9: Dividend, Value | T9: Dry bulk shipping. Grain and fertilizer transport.
H10: =IFERROR(__xludf.DUMMYFUNCTION("IF(A10<>"""",googlefinance(A10,""price""),"""")"),"") | I10: =IF(F10<>"",F10*H10,"") | J10: =IF(F10<>"",F10*G10,"") | K10: =IF(J10<>"",I10-J10,"") | L10: =IF(AND(J10<>"",J10<>0),K10/J10,"") | M10: =IF(I10<>"",IF(SUM($I$2:$I$200)<>0,I10/SUM($I$2:$I$200),""),"")
H11: =IFERROR(__xludf.DUMMYFUNCTION("IF(A11<>"""",googlefinance(A11,""price""),"""")"),"") | I11: =IF(F11<>"",F11*H11,"") | J11: =IF(F11<>"",F11*G11,"") | K11: =IF(J11<>"",I11-J11,"") | L11: =IF(AND(J11<>"",J11<>0),K11/J11,"") | M11: =IF(I11<>"",IF(SUM($I$2:$I$200)<>0,I11/SUM($I$2:$I$200),""),"")
H12: =IFERROR(__xludf.DUMMYFUNCTION("IF(A12<>"""",googlefinance(A12,""price""),"""")"),"") | I12: =IF(F12<>"",F12*H12,"") | J12: =IF(F12<>"",F12*G12,"") | K12: =IF(J12<>"",I12-J12,"") | L12: =IF(AND(J12<>"",J12<>0),K12/J12,"") | M12: =IF(I12<>"",IF(SUM($I$2:$I$200)<>0,I12/SUM($I$2:$I$200),""),"")
H13: =IFERROR(__xludf.DUMMYFUNCTION("IF(A13<>"""",googlefinance(A13,""price""),"""")"),"") | I13: =IF(F13<>"",F13*H13,"") | J13: =IF(F13<>"",F13*G13,"") | K13: =IF(J13<>"",I13-J13,"") | L13: =IF(AND(J13<>"",J13<>0),K13/J13,"") | M13: =IF(I13<>"",IF(SUM($I$2:$I$200)<>0,I13/SUM($I$2:$I$200),""),"")
H14: =IFERROR(__xludf.DUMMYFUNCTION("IF(A14<>"""",googlefinance(A14,""price""),"""")"),"") | I14: =IF(F14<>"",F14*H14,"") | J14: =IF(F14<>"",F14*G14,"") | K14: =IF(J14<>"",I14-J14,"") | L14: =IF(AND(J14<>"",J14<>0),K14/J14,"") | M14: =IF(I14<>"",IF(SUM($I$2:$I$200)<>0,I14/SUM($I$2:$I$200),""),"")
H15: =IFERROR(__xludf.DUMMYFUNCTION("IF(A15<>"""",googlefinance(A15,""price""),"""")"),"") | I15: =IF(F15<>"",F15*H15,"") | J15: =IF(F15<>"",F15*G15,"") | K15: =IF(J15<>"",I15-J15,"") | L15: =IF(AND(J15<>"",J15<>0),K15/J15,"") | M15: =IF(I15<>"",IF(SUM($I$2:$I$200)<>0,I15/SUM($I$2:$I$200),""),"")
H16: =IFERROR(__xludf.DUMMYFUNCTION("IF(A16<>"""",googlefinance(A16,""price""),"""")"),"") | I16: =IF(F16<>"",F16*H16,"") | J16: =IF(F16<>"",F16*G16,"") | K16: =IF(J16<>"",I16-J16,"") | L16: =IF(AND(J16<>"",J16<>0),K16/J16,"") | M16: =IF(I16<>"",IF(SUM($I$2:$I$200)<>0,I16/SUM($I$2:$I$200),""),"")
H17: =IFERROR(__xludf.DUMMYFUNCTION("IF(A17<>"""",googlefinance(A17,""price""),"""")"),"") | I17: =IF(F17<>"",F17*H17,"") | J17: =IF(F17<>"",F17*G17,"") | K17: =IF(J17<>"",I17-J17,"") | L17: =IF(AND(J17<>"",J17<>0),K17/J17,"") | M17: =IF(I17<>"",IF(SUM($I$2:$I$200)<>0,I17/SUM($I$2:$I$200),""),"")
H18: =IFERROR(__xludf.DUMMYFUNCTION("IF(A18<>"""",googlefinance(A18,""price""),"""")"),"") | I18: =IF(F18<>"",F18*H18,"") | J18: =IF(F18<>"",F18*G18,"") | K18: =IF(J18<>"",I18-J18,"") | L18: =IF(AND(J18<>"",J18<>0),K18/J18,"") | M18: =IF(I18<>"",IF(SUM($I$2:$I$200)<>0,I18/SUM($I$2:$I$200),""),"")
H19: =IFERROR(__xludf.DUMMYFUNCTION("IF(A19<>"""",googlefinance(A19,""price""),"""")"),"") | I19: =IF(F19<>"",F19*H19,"") | J19: =IF(F19<>"",F19*G19,"") | K19: =IF(J19<>"",I19-J19,"") | L19: =IF(AND(J19<>"",J19<>0),K19/J19,"") | M19: =IF(I19<>"",IF(SUM($I$2:$I$200)<>0,I19/SUM($I$2:$I$200),""),"")
H20: =IFERROR(__xludf.DUMMYFUNCTION("IF(A20<>"""",googlefinance(A20,""price""),"""")"),"") | I20: =IF(F20<>"",F20*H20,"") | J20: =IF(F20<>"",F20*G20,"") | K20: =IF(J20<>"",I20-J20,"") | L20: =IF(AND(J20<>"",J20<>0),K20/J20,"") | M20: =IF(I20<>"",IF(SUM($I$2:$I$200)<>0,I20/SUM($I$2:$I$200),""),"")
H21: =IFERROR(__xludf.DUMMYFUNCTION("IF(A21<>"""",googlefinance(A21,""price""),"""")"),"") | I21: =IF(F21<>"",F21*H21,"") | J21: =IF(F21<>"",F21*G21,"") | K21: =IF(J21<>"",I21-J21,"") | L21: =IF(AND(J21<>"",J21<>0),K21/J21,"") | M21: =IF(I21<>"",IF(SUM($I$2:$I$200)<>0,I21/SUM($I$2:$I$200),""),"")
H22: =IFERROR(__xludf.DUMMYFUNCTION("IF(A22<>"""",googlefinance(A22,""price""),"""")"),"") | I22: =IF(F22<>"",F22*H22,"") | J22: =IF(F22<>"",F22*G22,"") | K22: =IF(J22<>"",I22-J22,"") | L22: =IF(AND(J22<>"",J22<>0),K22/J22,"") | M22: =IF(I22<>"",IF(SUM($I$2:$I$200)<>0,I22/SUM($I$2:$I$200),""),"")
H23: =IFERROR(__xludf.DUMMYFUNCTION("IF(A23<>"""",googlefinance(A23,""price""),"""")"),"") | I23: =IF(F23<>"",F23*H23,"") | J23: =IF(F23<>"",F23*G23,"") | K23: =IF(J23<>"",I23-J23,"") | L23: =IF(AND(J23<>"",J23<>0),K23/J23,"") | M23: =IF(I23<>"",IF(SUM($I$2:$I$200)<>0,I23/SUM($I$2:$I$200),""),"")
H24: =IFERROR(__xludf.DUMMYFUNCTION("IF(A24<>"""",googlefinance(A24,""price""),"""")"),"") | I24: =IF(F24<>"",F24*H24,"") | J24: =IF(F24<>"",F24*G24,"") | K24: =IF(J24<>"",I24-J24,"") | L24: =IF(AND(J24<>"",J24<>0),K24/J24,"") | M24: =IF(I24<>"",IF(SUM($I$2:$I$200)<>0,I24/SUM($I$2:$I$200),""),"")
H25: =IFERROR(__xludf.DUMMYFUNCTION("IF(A25<>"""",googlefinance(A25,""price""),"""")"),"") | I25: =IF(F25<>"",F25*H25,"") | J25: =IF(F25<>"",F25*G25,"") | K25: =IF(J25<>"",I25-J25,"") | L25: =IF(AND(J25<>"",J25<>0),K25/J25,"") | M25: =IF(I25<>"",IF(SUM($I$2:$I$200)<>0,I25/SUM($I$2:$I$200),""),"")
H26: =IFERROR(__xludf.DUMMYFUNCTION("IF(A26<>"""",googlefinance(A26,""price""),"""")"),"") | I26: =IF(F26<>"",F26*H26,"") | J26: =IF(F26<>"",F26*G26,"") | K26: =IF(J26<>"",I26-J26,"") | L26: =IF(AND(J26<>"",J26<>0),K26/J26,"") | M26: =IF(I26<>"",IF(SUM($I$2:$I$200)<>0,I26/SUM($I$2:$I$200),""),"")
H27: =IFERROR(__xludf.DUMMYFUNCTION("IF(A27<>"""",googlefinance(A27,""price""),"""")"),"") | I27: =IF(F27<>"",F27*H27,"") | J27: =IF(F27<>"",F27*G27,"") | K27: =IF(J27<>"",I27-J27,"") | L27: =IF(AND(J27<>"",J27<>0),K27/J27,"") | M27: =IF(I27<>"",IF(SUM($I$2:$I$200)<>0,I27/SUM($I$2:$I$200),""),"")
H28: =IFERROR(__xludf.DUMMYFUNCTION("IF(A28<>"""",googlefinance(A28,""price""),"""")"),"") | I28: =IF(F28<>"",F28*H28,"") | J28: =IF(F28<>"",F28*G28,"") | K28: =IF(J28<>"",I28-J28,"") | L28: =IF(AND(J28<>"",J28<>0),K28/J28,"") | M28: =IF(I28<>"",IF(SUM($I$2:$I$200)<>0,I28/SUM($I$2:$I$200),""),"")
H29: =IFERROR(__xludf.DUMMYFUNCTION("IF(A29<>"""",googlefinance(A29,""price""),"""")"),"") | I29: =IF(F29<>"",F29*H29,"") | J29: =IF(F29<>"",F29*G29,"") | K29: =IF(J29<>"",I29-J29,"") | L29: =IF(AND(J29<>"",J29<>0),K29/J29,"") | M29: =IF(I29<>"",IF(SUM($I$2:$I$200)<>0,I29/SUM($I$2:$I$200),""),"")
H30: =IFERROR(__xludf.DUMMYFUNCTION("IF(A30<>"""",googlefinance(A30,""price""),"""")"),"") | I30: =IF(F30<>"",F30*H30,"") | J30: =IF(F30<>"",F30*G30,"") | K30: =IF(J30<>"",I30-J30,"") | L30: =IF(AND(J30<>"",J30<>0),K30/J30,"") | M30: =IF(I30<>"",IF(SUM($I$2:$I$200)<>0,I30/SUM($I$2:$I$200),""),"")
H31: =IFERROR(__xludf.DUMMYFUNCTION("IF(A31<>"""",googlefinance(A31,""price""),"""")"),"") | I31: =IF(F31<>"",F31*H31,"") | J31: =IF(F31<>"",F31*G31,"") | K31: =IF(J31<>"",I31-J31,"") | L31: =IF(AND(J31<>"",J31<>0),K31/J31,"") | M31: =IF(I31<>"",IF(SUM($I$2:$I$200)<>0,I31/SUM($I$2:$I$200),""),"")
H32: =IFERROR(__xludf.DUMMYFUNCTION("IF(A32<>"""",googlefinance(A32,""price""),"""")"),"") | I32: =IF(F32<>"",F32*H32,"") | J32: =IF(F32<>"",F32*G32,"") | K32: =IF(J32<>"",I32-J32,"") | L32: =IF(AND(J32<>"",J32<>0),K32/J32,"") | M32: =IF(I32<>"",IF(SUM($I$2:$I$200)<>0,I32/SUM($I$2:$I$200),""),"")
H33: =IFERROR(__xludf.DUMMYFUNCTION("IF(A33<>"""",googlefinance(A33,""price""),"""")"),"") | I33: =IF(F33<>"",F33*H33,"") | J33: =IF(F33<>"",F33*G33,"") | K33: =IF(J33<>"",I33-J33,"") | L33: =IF(AND(J33<>"",J33<>0),K33/J33,"") | M33: =IF(I33<>"",IF(SUM($I$2:$I$200)<>0,I33/SUM($I$2:$I$200),""),"")
H34: =IFERROR(__xludf.DUMMYFUNCTION("IF(A34<>"""",googlefinance(A34,""price""),"""")"),"") | I34: =IF(F34<>"",F34*H34,"") | J34: =IF(F34<>"",F34*G34,"") | K34: =IF(J34<>"",I34-J34,"") | L34: =IF(AND(J34<>"",J34<>0),K34/J34,"") | M34: =IF(I34<>"",IF(SUM($I$2:$I$200)<>0,I34/SUM($I$2:$I$200),""),"")
H35: =IFERROR(__xludf.DUMMYFUNCTION("IF(A35<>"""",googlefinance(A35,""price""),"""")"),"") | I35: =IF(F35<>"",F35*H35,"") | J35: =IF(F35<>"",F35*G35,"") | K35: =IF(J35<>"",I35-J35,"") | L35: =IF(AND(J35<>"",J35<>0),K35/J35,"") | M35: =IF(I35<>"",IF(SUM($I$2:$I$200)<>0,I35/SUM($I$2:$I$200),""),"")
H36: =IFERROR(__xludf.DUMMYFUNCTION("IF(A36<>"""",googlefinance(A36,""price""),"""")"),"") | I36: =IF(F36<>"",F36*H36,"") | J36: =IF(F36<>"",F36*G36,"") | K36: =IF(J36<>"",I36-J36,"") | L36: =IF(AND(J36<>"",J36<>0),K36/J36,"") | M36: =IF(I36<>"",IF(SUM($I$2:$I$200)<>0,I36/SUM($I$2:$I$200),""),"")
H37: =IFERROR(__xludf.DUMMYFUNCTION("IF(A37<>"""",googlefinance(A37,""price""),"""")"),"") | I37: =IF(F37<>"",F37*H37,"") | J37: =IF(F37<>"",F37*G37,"") | K37: =IF(J37<>"",I37-J37,"") | L37: =IF(AND(J37<>"",J37<>0),K37/J37,"") | M37: =IF(I37<>"",IF(SUM($I$2:$I$200)<>0,I37/SUM($I$2:$I$200),""),"")
H38: =IFERROR(__xludf.DUMMYFUNCTION("IF(A38<>"""",googlefinance(A38,""price""),"""")"),"") | I38: =IF(F38<>"",F38*H38,"") | J38: =IF(F38<>"",F38*G38,"") | K38: =IF(J38<>"",I38-J38,"") | L38: =IF(AND(J38<>"",J38<>0),K38/J38,"") | M38: =IF(I38<>"",IF(SUM($I$2:$I$200)<>0,I38/SUM($I$2:$I$200),""),"")
H39: =IFERROR(__xludf.DUMMYFUNCTION("IF(A39<>"""",googlefinance(A39,""price""),"""")"),"") | I39: =IF(F39<>"",F39*H39,"") | J39: =IF(F39<>"",F39*G39,"") | K39: =IF(J39<>"",I39-J39,"") | L39: =IF(AND(J39<>"",J39<>0),K39/J39,"") | M39: =IF(I39<>"",IF(SUM($I$2:$I$200)<>0,I39/SUM($I$2:$I$200),""),"")
H40: =IFERROR(__xludf.DUMMYFUNCTION("IF(A40<>"""",googlefinance(A40,""price""),"""")"),"") | I40: =IF(F40<>"",F40*H40,"") | J40: =IF(F40<>"",F40*G40,"") | K40: =IF(J40<>"",I40-J40,"") | L40: =IF(AND(J40<>"",J40<>0),K40/J40,"") | M40: =IF(I40<>"",IF(SUM($I$2:$I$200)<>0,I40/SUM($I$2:$I$200),""),"")
H41: =IFERROR(__xludf.DUMMYFUNCTION("IF(A41<>"""",googlefinance(A41,""price""),"""")"),"") | I41: =IF(F41<>"",F41*H41,"") | J41: =IF(F41<>"",F41*G41,"") | K41: =IF(J41<>"",I41-J41,"") | L41: =IF(AND(J41<>"",J41<>0),K41/J41,"") | M41: =IF(I41<>"",IF(SUM($I$2:$I$200)<>0,I41/SUM($I$2:$I$200),""),"")
H42: =IFERROR(__xludf.DUMMYFUNCTION("IF(A42<>"""",googlefinance(A42,""price""),"""")"),"") | I42: =IF(F42<>"",F42*H42,"") | J42: =IF(F42<>"",F42*G42,"") | K42: =IF(J42<>"",I42-J42,"") | L42: =IF(AND(J42<>"",J42<>0),K42/J42,"") | M42: =IF(I42<>"",IF(SUM($I$2:$I$200)<>0,I42/SUM($I$2:$I$200),""),"")
H43: =IFERROR(__xludf.DUMMYFUNCTION("IF(A43<>"""",googlefinance(A43,""price""),"""")"),"") | I43: =IF(F43<>"",F43*H43,"") | J43: =IF(F43<>"",F43*G43,"") | K43: =IF(J43<>"",I43-J43,"") | L43: =IF(AND(J43<>"",J43<>0),K43/J43,"") | M43: =IF(I43<>"",IF(SUM($I$2:$I$200)<>0,I43/SUM($I$2:$I$200),""),"")
H44: =IFERROR(__xludf.DUMMYFUNCTION("IF(A44<>"""",googlefinance(A44,""price""),"""")"),"") | I44: =IF(F44<>"",F44*H44,"") | J44: =IF(F44<>"",F44*G44,"") | K44: =IF(J44<>"",I44-J44,"") | L44: =IF(AND(J44<>"",J44<>0),K44/J44,"") | M44: =IF(I44<>"",IF(SUM($I$2:$I$200)<>0,I44/SUM($I$2:$I$200),""),"")
H45: =IFERROR(__xludf.DUMMYFUNCTION("IF(A45<>"""",googlefinance(A45,""price""),"""")"),"") | I45: =IF(F45<>"",F45*H45,"") | J45: =IF(F45<>"",F45*G45,"") | K45: =IF(J45<>"",I45-J45,"") | L45: =IF(AND(J45<>"",J45<>0),K45/J45,"") | M45: =IF(I45<>"",IF(SUM($I$2:$I$200)<>0,I45/SUM($I$2:$I$200),""),"")
H46: =IFERROR(__xludf.DUMMYFUNCTION("IF(A46<>"""",googlefinance(A46,""price""),"""")"),"") | I46: =IF(F46<>"",F46*H46,"") | J46: =IF(F46<>"",F46*G46,"") | K46: =IF(J46<>"",I46-J46,"") | L46: =IF(AND(J46<>"",J46<>0),K46/J46,"") | M46: =IF(I46<>"",IF(SUM($I$2:$I$200)<>0,I46/SUM($I$2:$I$200),""),"")
H47: =IFERROR(__xludf.DUMMYFUNCTION("IF(A47<>"""",googlefinance(A47,""price""),"""")"),"") | I47: =IF(F47<>"",F47*H47,"") | J47: =IF(F47<>"",F47*G47,"") | K47: =IF(J47<>"",I47-J47,"") | L47: =IF(AND(J47<>"",J47<>0),K47/J47,"") | M47: =IF(I47<>"",IF(SUM($I$2:$I$200)<>0,I47/SUM($I$2:$I$200),""),"")
H48: =IFERROR(__xludf.DUMMYFUNCTION("IF(A48<>"""",googlefinance(A48,""price""),"""")"),"") | I48: =IF(F48<>"",F48*H48,"") | J48: =IF(F48<>"",F48*G48,"") | K48: =IF(J48<>"",I48-J48,"") | L48: =IF(AND(J48<>"",J48<>0),K48/J48,"") | M48: =IF(I48<>"",IF(SUM($I$2:$I$200)<>0,I48/SUM($I$2:$I$200),""),"")
H49: =IFERROR(__xludf.DUMMYFUNCTION("IF(A49<>"""",googlefinance(A49,""price""),"""")"),"") | I49: =IF(F49<>"",F49*H49,"") | J49: =IF(F49<>"",F49*G49,"") | K49: =IF(J49<>"",I49-J49,"") | L49: =IF(AND(J49<>"",J49<>0),K49/J49,"") | M49: =IF(I49<>"",IF(SUM($I$2:$I$200)<>0,I49/SUM($I$2:$I$200),""),"")
H50: =IFERROR(__xludf.DUMMYFUNCTION("IF(A50<>"""",googlefinance(A50,""price""),"""")"),"") | I50: =IF(F50<>"",F50*H50,"") | J50: =IF(F50<>"",F50*G50,"") | K50: =IF(J50<>"",I50-J50,"") | L50: =IF(AND(J50<>"",J50<>0),K50/J50,"") | M50: =IF(I50<>"",IF(SUM($I$2:$I$200)<>0,I50/SUM($I$2:$I$200),""),"")
H51: =IFERROR(__xludf.DUMMYFUNCTION("IF(A51<>"""",googlefinance(A51,""price""),"""")"),"") | I51: =IF(F51<>"",F51*H51,"") | J51: =IF(F51<>"",F51*G51,"") | K51: =IF(J51<>"",I51-J51,"") | L51: =IF(AND(J51<>"",J51<>0),K51/J51,"") | M51: =IF(I51<>"",IF(SUM($I$2:$I$200)<>0,I51/SUM($I$2:$I$200),""),"")
H52: =IFERROR(__xludf.DUMMYFUNCTION("IF(A52<>"""",googlefinance(A52,""price""),"""")"),"") | I52: =IF(F52<>"",F52*H52,"") | J52: =IF(F52<>"",F52*G52,"") | K52: =IF(J52<>"",I52-J52,"") | L52: =IF(AND(J52<>"",J52<>0),K52/J52,"") | M52: =IF(I52<>"",IF(SUM($I$2:$I$200)<>0,I52/SUM($I$2:$I$200),""),"")
H53: =IFERROR(__xludf.DUMMYFUNCTION("IF(A53<>"""",googlefinance(A53,""price""),"""")"),"") | I53: =IF(F53<>"",F53*H53,"") | J53: =IF(F53<>"",F53*G53,"") | K53: =IF(J53<>"",I53-J53,"") | L53: =IF(AND(J53<>"",J53<>0),K53/J53,"") | M53: =IF(I53<>"",IF(SUM($I$2:$I$200)<>0,I53/SUM($I$2:$I$200),""),"")
H54: =IFERROR(__xludf.DUMMYFUNCTION("IF(A54<>"""",googlefinance(A54,""price""),"""")"),"") | I54: =IF(F54<>"",F54*H54,"") | J54: =IF(F54<>"",F54*G54,"") | K54: =IF(J54<>"",I54-J54,"") | L54: =IF(AND(J54<>"",J54<>0),K54/J54,"") | M54: =IF(I54<>"",IF(SUM($I$2:$I$200)<>0,I54/SUM($I$2:$I$200),""),"")
H55: =IFERROR(__xludf.DUMMYFUNCTION("IF(A55<>"""",googlefinance(A55,""price""),"""")"),"") | I55: =IF(F55<>"",F55*H55,"") | J55: =IF(F55<>"",F55*G55,"") | K55: =IF(J55<>"",I55-J55,"") | L55: =IF(AND(J55<>"",J55<>0),K55/J55,"") | M55: =IF(I55<>"",IF(SUM($I$2:$I$200)<>0,I55/SUM($I$2:$I$200),""),"")
H56: =IFERROR(__xludf.DUMMYFUNCTION("IF(A56<>"""",googlefinance(A56,""price""),"""")"),"") | I56: =IF(F56<>"",F56*H56,"") | J56: =IF(F56<>"",F56*G56,"") | K56: =IF(J56<>"",I56-J56,"") | L56: =IF(AND(J56<>"",J56<>0),K56/J56,"") | M56: =IF(I56<>"",IF(SUM($I$2:$I$200)<>0,I56/SUM($I$2:$I$200),""),"")
H57: =IFERROR(__xludf.DUMMYFUNCTION("IF(A57<>"""",googlefinance(A57,""price""),"""")"),"") | I57: =IF(F57<>"",F57*H57,"") | J57: =IF(F57<>"",F57*G57,"") | K57: =IF(J57<>"",I57-J57,"") | L57: =IF(AND(J57<>"",J57<>0),K57/J57,"") | M57: =IF(I57<>"",IF(SUM($I$2:$I$200)<>0,I57/SUM($I$2:$I$200),""),"")
H58: =IFERROR(__xludf.DUMMYFUNCTION("IF(A58<>"""",googlefinance(A58,""price""),"""")"),"") | I58: =IF(F58<>"",F58*H58,"") | J58: =IF(F58<>"",F58*G58,"") | K58: =IF(J58<>"",I58-J58,"") | L58: =IF(AND(J58<>"",J58<>0),K58/J58,"") | M58: =IF(I58<>"",IF(SUM($I$2:$I$200)<>0,I58/SUM($I$2:$I$200),""),"")
H59: =IFERROR(__xludf.DUMMYFUNCTION("IF(A59<>"""",googlefinance(A59,""price""),"""")"),"") | I59: =IF(F59<>"",F59*H59,"") | J59: =IF(F59<>"",F59*G59,"") | K59: =IF(J59<>"",I59-J59,"") | L59: =IF(AND(J59<>"",J59<>0),K59/J59,"") | M59: =IF(I59<>"",IF(SUM($I$2:$I$200)<>0,I59/SUM($I$2:$I$200),""),"")
H60: =IFERROR(__xludf.DUMMYFUNCTION("IF(A60<>"""",googlefinance(A60,""price""),"""")"),"") | I60: =IF(F60<>"",F60*H60,"") | J60: =IF(F60<>"",F60*G60,"") | K60: =IF(J60<>"",I60-J60,"") | L60: =IF(AND(J60<>"",J60<>0),K60/J60,"") | M60: =IF(I60<>"",IF(SUM($I$2:$I$200)<>0,I60/SUM($I$2:$I$200),""),"")
H61: =IFERROR(__xludf.DUMMYFUNCTION("IF(A61<>"""",googlefinance(A61,""price""),"""")"),"") | I61: =IF(F61<>"",F61*H61,"") | J61: =IF(F61<>"",F61*G61,"") | K61: =IF(J61<>"",I61-J61,"") | L61: =IF(AND(J61<>"",J61<>0),K61/J61,"") | M61: =IF(I61<>"",IF(SUM($I$2:$I$200)<>0,I61/SUM($I$2:$I$200),""),"")
H62: =IFERROR(__xludf.DUMMYFUNCTION("IF(A62<>"""",googlefinance(A62,""price""),"""")"),"") | I62: =IF(F62<>"",F62*H62,"") | J62: =IF(F62<>"",F62*G62,"") | K62: =IF(J62<>"",I62-J62,"") | L62: =IF(AND(J62<>"",J62<>0),K62/J62,"") | M62: =IF(I62<>"",IF(SUM($I$2:$I$200)<>0,I62/SUM($I$2:$I$200),""),"")
H63: =IFERROR(__xludf.DUMMYFUNCTION("IF(A63<>"""",googlefinance(A63,""price""),"""")"),"") | I63: =IF(F63<>"",F63*H63,"") | J63: =IF(F63<>"",F63*G63,"") | K63: =IF(J63<>"",I63-J63,"") | L63: =IF(AND(J63<>"",J63<>0),K63/J63,"") | M63: =IF(I63<>"",IF(SUM($I$2:$I$200)<>0,I63/SUM($I$2:$I$200),""),"")
H64: =IFERROR(__xludf.DUMMYFUNCTION("IF(A64<>"""",googlefinance(A64,""price""),"""")"),"") | I64: =IF(F64<>"",F64*H64,"") | J64: =IF(F64<>"",F64*G64,"") | K64: =IF(J64<>"",I64-J64,"") | L64: =IF(AND(J64<>"",J64<>0),K64/J64,"") | M64: =IF(I64<>"",IF(SUM($I$2:$I$200)<>0,I64/SUM($I$2:$I$200),""),"")
H65: =IFERROR(__xludf.DUMMYFUNCTION("IF(A65<>"""",googlefinance(A65,""price""),"""")"),"") | I65: =IF(F65<>"",F65*H65,"") | J65: =IF(F65<>"",F65*G65,"") | K65: =IF(J65<>"",I65-J65,"") | L65: =IF(AND(J65<>"",J65<>0),K65/J65,"") | M65: =IF(I65<>"",IF(SUM($I$2:$I$200)<>0,I65/SUM($I$2:$I$200),""),"")
H66: =IFERROR(__xludf.DUMMYFUNCTION("IF(A66<>"""",googlefinance(A66,""price""),"""")"),"") | I66: =IF(F66<>"",F66*H66,"") | J66: =IF(F66<>"",F66*G66,"") | K66: =IF(J66<>"",I66-J66,"") | L66: =IF(AND(J66<>"",J66<>0),K66/J66,"") | M66: =IF(I66<>"",IF(SUM($I$2:$I$200)<>0,I66/SUM($I$2:$I$200),""),"")
H67: =IFERROR(__xludf.DUMMYFUNCTION("IF(A67<>"""",googlefinance(A67,""price""),"""")"),"") | I67: =IF(F67<>"",F67*H67,"") | J67: =IF(F67<>"",F67*G67,"") | K67: =IF(J67<>"",I67-J67,"") | L67: =IF(AND(J67<>"",J67<>0),K67/J67,"") | M67: =IF(I67<>"",IF(SUM($I$2:$I$200)<>0,I67/SUM($I$2:$I$200),""),"")
H68: =IFERROR(__xludf.DUMMYFUNCTION("IF(A68<>"""",googlefinance(A68,""price""),"""")"),"") | I68: =IF(F68<>"",F68*H68,"") | J68: =IF(F68<>"",F68*G68,"") | K68: =IF(J68<>"",I68-J68,"") | L68: =IF(AND(J68<>"",J68<>0),K68/J68,"") | M68: =IF(I68<>"",IF(SUM($I$2:$I$200)<>0,I68/SUM($I$2:$I$200),""),"")
H69: =IFERROR(__xludf.DUMMYFUNCTION("IF(A69<>"""",googlefinance(A69,""price""),"""")"),"") | I69: =IF(F69<>"",F69*H69,"") | J69: =IF(F69<>"",F69*G69,"") | K69: =IF(J69<>"",I69-J69,"") | L69: =IF(AND(J69<>"",J69<>0),K69/J69,"") | M69: =IF(I69<>"",IF(SUM($I$2:$I$200)<>0,I69/SUM($I$2:$I$200),""),"")
H70: =IFERROR(__xludf.DUMMYFUNCTION("IF(A70<>"""",googlefinance(A70,""price""),"""")"),"") | I70: =IF(F70<>"",F70*H70,"") | J70: =IF(F70<>"",F70*G70,"") | K70: =IF(J70<>"",I70-J70,"") | L70: =IF(AND(J70<>"",J70<>0),K70/J70,"") | M70: =IF(I70<>"",IF(SUM($I$2:$I$200)<>0,I70/SUM($I$2:$I$200),""),"")
H71: =IFERROR(__xludf.DUMMYFUNCTION("IF(A71<>"""",googlefinance(A71,""price""),"""")"),"") | I71: =IF(F71<>"",F71*H71,"") | J71: =IF(F71<>"",F71*G71,"") | K71: =IF(J71<>"",I71-J71,"") | L71: =IF(AND(J71<>"",J71<>0),K71/J71,"") | M71: =IF(I71<>"",IF(SUM($I$2:$I$200)<>0,I71/SUM($I$2:$I$200),""),"")
H72: =IFERROR(__xludf.DUMMYFUNCTION("IF(A72<>"""",googlefinance(A72,""price""),"""")"),"") | I72: =IF(F72<>"",F72*H72,"") | J72: =IF(F72<>"",F72*G72,"") | K72: =IF(J72<>"",I72-J72,"") | L72: =IF(AND(J72<>"",J72<>0),K72/J72,"") | M72: =IF(I72<>"",IF(SUM($I$2:$I$200)<>0,I72/SUM($I$2:$I$200),""),"")
H73: =IFERROR(__xludf.DUMMYFUNCTION("IF(A73<>"""",googlefinance(A73,""price""),"""")"),"") | I73: =IF(F73<>"",F73*H73,"") | J73: =IF(F73<>"",F73*G73,"") | K73: =IF(J73<>"",I73-J73,"") | L73: =IF(AND(J73<>"",J73<>0),K73/J73,"") | M73: =IF(I73<>"",IF(SUM($I$2:$I$200)<>0,I73/SUM($I$2:$I$200),""),"")
H74: =IFERROR(__xludf.DUMMYFUNCTION("IF(A74<>"""",googlefinance(A74,""price""),"""")"),"") | I74: =IF(F74<>"",F74*H74,"") | J74: =IF(F74<>"",F74*G74,"") | K74: =IF(J74<>"",I74-J74,"") | L74: =IF(AND(J74<>"",J74<>0),K74/J74,"") | M74: =IF(I74<>"",IF(SUM($I$2:$I$200)<>0,I74/SUM($I$2:$I$200),""),"")
H75: =IFERROR(__xludf.DUMMYFUNCTION("IF(A75<>"""",googlefinance(A75,""price""),"""")"),"") | I75: =IF(F75<>"",F75*H75,"") | J75: =IF(F75<>"",F75*G75,"") | K75: =IF(J75<>"",I75-J75,"") | L75: =IF(AND(J75<>"",J75<>0),K75/J75,"") | M75: =IF(I75<>"",IF(SUM($I$2:$I$200)<>0,I75/SUM($I$2:$I$200),""),"")
H76: =IFERROR(__xludf.DUMMYFUNCTION("IF(A76<>"""",googlefinance(A76,""price""),"""")"),"") | I76: =IF(F76<>"",F76*H76,"") | J76: =IF(F76<>"",F76*G76,"") | K76: =IF(J76<>"",I76-J76,"") | L76: =IF(AND(J76<>"",J76<>0),K76/J76,"") | M76: =IF(I76<>"",IF(SUM($I$2:$I$200)<>0,I76/SUM($I$2:$I$200),""),"")
H77: =IFERROR(__xludf.DUMMYFUNCTION("IF(A77<>"""",googlefinance(A77,""price""),"""")"),"") | I77: =IF(F77<>"",F77*H77,"") | J77: =IF(F77<>"",F77*G77,"") | K77: =IF(J77<>"",I77-J77,"") | L77: =IF(AND(J77<>"",J77<>0),K77/J77,"") | M77: =IF(I77<>"",IF(SUM($I$2:$I$200)<>0,I77/SUM($I$2:$I$200),""),"")
H78: =IFERROR(__xludf.DUMMYFUNCTION("IF(A78<>"""",googlefinance(A78,""price""),"""")"),"") | I78: =IF(F78<>"",F78*H78,"") | J78: =IF(F78<>"",F78*G78,"") | K78: =IF(J78<>"",I78-J78,"") | L78: =IF(AND(J78<>"",J78<>0),K78/J78,"") | M78: =IF(I78<>"",IF(SUM($I$2:$I$200)<>0,I78/SUM($I$2:$I$200),""),"")
H79: =IFERROR(__xludf.DUMMYFUNCTION("IF(A79<>"""",googlefinance(A79,""price""),"""")"),"") | I79: =IF(F79<>"",F79*H79,"") | J79: =IF(F79<>"",F79*G79,"") | K79: =IF(J79<>"",I79-J79,"") | L79: =IF(AND(J79<>"",J79<>0),K79/J79,"") | M79: =IF(I79<>"",IF(SUM($I$2:$I$200)<>0,I79/SUM($I$2:$I$200),""),"")
H80: =IFERROR(__xludf.DUMMYFUNCTION("IF(A80<>"""",googlefinance(A80,""price""),"""")"),"") | I80: =IF(F80<>"",F80*H80,"") | J80: =IF(F80<>"",F80*G80,"") | K80: =IF(J80<>"",I80-J80,"") | L80: =IF(AND(J80<>"",J80<>0),K80/J80,"") | M80: =IF(I80<>"",IF(SUM($I$2:$I$200)<>0,I80/SUM($I$2:$I$200),""),"")
H81: =IFERROR(__xludf.DUMMYFUNCTION("IF(A81<>"""",googlefinance(A81,""price""),"""")"),"") | I81: =IF(F81<>"",F81*H81,"") | J81: =IF(F81<>"",F81*G81,"") | K81: =IF(J81<>"",I81-J81,"") | L81: =IF(AND(J81<>"",J81<>0),K81/J81,"") | M81: =IF(I81<>"",IF(SUM($I$2:$I$200)<>0,I81/SUM($I$2:$I$200),""),"")
H82: =IFERROR(__xludf.DUMMYFUNCTION("IF(A82<>"""",googlefinance(A82,""price""),"""")"),"") | I82: =IF(F82<>"",F82*H82,"") | J82: =IF(F82<>"",F82*G82,"") | K82: =IF(J82<>"",I82-J82,"") | L82: =IF(AND(J82<>"",J82<>0),K82/J82,"") | M82: =IF(I82<>"",IF(SUM($I$2:$I$200)<>0,I82/SUM($I$2:$I$200),""),"")
H83: =IFERROR(__xludf.DUMMYFUNCTION("IF(A83<>"""",googlefinance(A83,""price""),"""")"),"") | I83: =IF(F83<>"",F83*H83,"") | J83: =IF(F83<>"",F83*G83,"") | K83: =IF(J83<>"",I83-J83,"") | L83: =IF(AND(J83<>"",J83<>0),K83/J83,"") | M83: =IF(I83<>"",IF(SUM($I$2:$I$200)<>0,I83/SUM($I$2:$I$200),""),"")
H84: =IFERROR(__xludf.DUMMYFUNCTION("IF(A84<>"""",googlefinance(A84,""price""),"""")"),"") | I84: =IF(F84<>"",F84*H84,"") | J84: =IF(F84<>"",F84*G84,"") | K84: =IF(J84<>"",I84-J84,"") | L84: =IF(AND(J84<>"",J84<>0),K84/J84,"") | M84: =IF(I84<>"",IF(SUM($I$2:$I$200)<>0,I84/SUM($I$2:$I$200),""),"")
H85: =IFERROR(__xludf.DUMMYFUNCTION("IF(A85<>"""",googlefinance(A85,""price""),"""")"),"") | I85: =IF(F85<>"",F85*H85,"") | J85: =IF(F85<>"",F85*G85,"") | K85: =IF(J85<>"",I85-J85,"") | L85: =IF(AND(J85<>"",J85<>0),K85/J85,"") | M85: =IF(I85<>"",IF(SUM($I$2:$I$200)<>0,I85/SUM($I$2:$I$200),""),"")
H86: =IFERROR(__xludf.DUMMYFUNCTION("IF(A86<>"""",googlefinance(A86,""price""),"""")"),"") | I86: =IF(F86<>"",F86*H86,"") | J86: =IF(F86<>"",F86*G86,"") | K86: =IF(J86<>"",I86-J86,"") | L86: =IF(AND(J86<>"",J86<>0),K86/J86,"") | M86: =IF(I86<>"",IF(SUM($I$2:$I$200)<>0,I86/SUM($I$2:$I$200),""),"")
H87: =IFERROR(__xludf.DUMMYFUNCTION("IF(A87<>"""",googlefinance(A87,""price""),"""")"),"") | I87: =IF(F87<>"",F87*H87,"") | J87: =IF(F87<>"",F87*G87,"") | K87: =IF(J87<>"",I87-J87,"") | L87: =IF(AND(J87<>"",J87<>0),K87/J87,"") | M87: =IF(I87<>"",IF(SUM($I$2:$I$200)<>0,I87/SUM($I$2:$I$200),""),"")
H88: =IFERROR(__xludf.DUMMYFUNCTION("IF(A88<>"""",googlefinance(A88,""price""),"""")"),"") | I88: =IF(F88<>"",F88*H88,"") | J88: =IF(F88<>"",F88*G88,"") | K88: =IF(J88<>"",I88-J88,"") | L88: =IF(AND(J88<>"",J88<>0),K88/J88,"") | M88: =IF(I88<>"",IF(SUM($I$2:$I$200)<>0,I88/SUM($I$2:$I$200),""),"")
H89: =IFERROR(__xludf.DUMMYFUNCTION("IF(A89<>"""",googlefinance(A89,""price""),"""")"),"") | I89: =IF(F89<>"",F89*H89,"") | J89: =IF(F89<>"",F89*G89,"") | K89: =IF(J89<>"",I89-J89,"") | L89: =IF(AND(J89<>"",J89<>0),K89/J89,"") | M89: =IF(I89<>"",IF(SUM($I$2:$I$200)<>0,I89/SUM($I$2:$I$200),""),"")
H90: =IFERROR(__xludf.DUMMYFUNCTION("IF(A90<>"""",googlefinance(A90,""price""),"""")"),"") | I90: =IF(F90<>"",F90*H90,"") | J90: =IF(F90<>"",F90*G90,"") | K90: =IF(J90<>"",I90-J90,"") | L90: =IF(AND(J90<>"",J90<>0),K90/J90,"") | M90: =IF(I90<>"",IF(SUM($I$2:$I$200)<>0,I90/SUM($I$2:$I$200),""),"")
H91: =IFERROR(__xludf.DUMMYFUNCTION("IF(A91<>"""",googlefinance(A91,""price""),"""")"),"") | I91: =IF(F91<>"",F91*H91,"") | J91: =IF(F91<>"",F91*G91,"") | K91: =IF(J91<>"",I91-J91,"") | L91: =IF(AND(J91<>"",J91<>0),K91/J91,"") | M91: =IF(I91<>"",IF(SUM($I$2:$I$200)<>0,I91/SUM($I$2:$I$200),""),"")
H92: =IFERROR(__xludf.DUMMYFUNCTION("IF(A92<>"""",googlefinance(A92,""price""),"""")"),"") | I92: =IF(F92<>"",F92*H92,"") | J92: =IF(F92<>"",F92*G92,"") | K92: =IF(J92<>"",I92-J92,"") | L92: =IF(AND(J92<>"",J92<>0),K92/J92,"") | M92: =IF(I92<>"",IF(SUM($I$2:$I$200)<>0,I92/SUM($I$2:$I$200),""),"")
H93: =IFERROR(__xludf.DUMMYFUNCTION("IF(A93<>"""",googlefinance(A93,""price""),"""")"),"") | I93: =IF(F93<>"",F93*H93,"") | J93: =IF(F93<>"",F93*G93,"") | K93: =IF(J93<>"",I93-J93,"") | L93: =IF(AND(J93<>"",J93<>0),K93/J93,"") | M93: =IF(I93<>"",IF(SUM($I$2:$I$200)<>0,I93/SUM($I$2:$I$200),""),"")
H94: =IFERROR(__xludf.DUMMYFUNCTION("IF(A94<>"""",googlefinance(A94,""price""),"""")"),"") | I94: =IF(F94<>"",F94*H94,"") | J94: =IF(F94<>"",F94*G94,"") | K94: =IF(J94<>"",I94-J94,"") | L94: =IF(AND(J94<>"",J94<>0),K94/J94,"") | M94: =IF(I94<>"",IF(SUM($I$2:$I$200)<>0,I94/SUM($I$2:$I$200),""),"")
H95: =IFERROR(__xludf.DUMMYFUNCTION("IF(A95<>"""",googlefinance(A95,""price""),"""")"),"") | I95: =IF(F95<>"",F95*H95,"") | J95: =IF(F95<>"",F95*G95,"") | K95: =IF(J95<>"",I95-J95,"") | L95: =IF(AND(J95<>"",J95<>0),K95/J95,"") | M95: =IF(I95<>"",IF(SUM($I$2:$I$200)<>0,I95/SUM($I$2:$I$200),""),"")
H96: =IFERROR(__xludf.DUMMYFUNCTION("IF(A96<>"""",googlefinance(A96,""price""),"""")"),"") | I96: =IF(F96<>"",F96*H96,"") | J96: =IF(F96<>"",F96*G96,"") | K96: =IF(J96<>"",I96-J96,"") | L96: =IF(AND(J96<>"",J96<>0),K96/J96,"") | M96: =IF(I96<>"",IF(SUM($I$2:$I$200)<>0,I96/SUM($I$2:$I$200),""),"")
H97: =IFERROR(__xludf.DUMMYFUNCTION("IF(A97<>"""",googlefinance(A97,""price""),"""")"),"") | I97: =IF(F97<>"",F97*H97,"") | J97: =IF(F97<>"",F97*G97,"") | K97: =IF(J97<>"",I97-J97,"") | L97: =IF(AND(J97<>"",J97<>0),K97/J97,"") | M97: =IF(I97<>"",IF(SUM($I$2:$I$200)<>0,I97/SUM($I$2:$I$200),""),"")
H98: =IFERROR(__xludf.DUMMYFUNCTION("IF(A98<>"""",googlefinance(A98,""price""),"""")"),"") | I98: =IF(F98<>"",F98*H98,"") | J98: =IF(F98<>"",F98*G98,"") | K98: =IF(J98<>"",I98-J98,"") | L98: =IF(AND(J98<>"",J98<>0),K98/J98,"") | M98: =IF(I98<>"",IF(SUM($I$2:$I$200)<>0,I98/SUM($I$2:$I$200),""),"")
H99: =IFERROR(__xludf.DUMMYFUNCTION("IF(A99<>"""",googlefinance(A99,""price""),"""")"),"") | I99: =IF(F99<>"",F99*H99,"") | J99: =IF(F99<>"",F99*G99,"") | K99: =IF(J99<>"",I99-J99,"") | L99: =IF(AND(J99<>"",J99<>0),K99/J99,"") | M99: =IF(I99<>"",IF(SUM($I$2:$I$200)<>0,I99/SUM($I$2:$I$200),""),"")
H100: =IFERROR(__xludf.DUMMYFUNCTION("IF(A100<>"""",googlefinance(A100,""price""),"""")"),"") | I100: =IF(F100<>"",F100*H100,"") | J100: =IF(F100<>"",F100*G100,"") | K100: =IF(J100<>"",I100-J100,"") | L100: =IF(AND(J100<>"",J100<>0),K100/J100,"") | M100: =IF(I100<>"",IF(SUM($I$2:$I$200)<>0,I100/SUM($I$2:$I$200),""),"")
...

Sheet Realized Trades
A1: Symbol | B1: Description | C1: Account | D1: Open Date | E1: Close Date | F1: Quantity | G1: Proceeds/Share | H1: Cost/Share | I1: Proceeds | J1: Cost Basis | K1: Gain/Loss $ | L1: Gain/Loss % | M1: Term | N1: Wash Sale? | O1: Disallowed Loss
A2: AAOI | B2: Applied Optoelectronics | C2: Individual | D2: 2026-03-05 | E2: 2026-03-10 | F2: 15 | G2: 124.5 | H2: 102.05 | I2: =F2*G2 -> 1867.5 | J2: =F2*H2 -> 1530.75 | K2: =I2-J2 -> 336.75 | L2: =IF(J2<>0,K2/J2,0) -> 0.2199902 | M2: =IF(AND(D2<>"",E2<>""),IF((DATEVALUE(E2)-DATEVALUE(D2))>365,"Long Term","Short Term"),"") -> Short Term
A3: LITE | B3: Lumentum Holdings | C3: Individual | D3: 2026-03-15 | E3: 2026-04-01 | F3: 15 | G3: 766 | H3: 726.37 | I3: =F3*G3 -> 11490 | J3: =F3*H3 -> 10895.55 | K3: =I3-J3 -> 594.45 | L3: =IF(J3<>0,K3/J3,0) -> 0.054558971 | M3: =IF(AND(D3<>"",E3<>""),IF((DATEVALUE(E3)-DATEVALUE(D3))>365,"Long Term","Short Term"),"") -> Short Term
A4: RIG | B4: Transocean | C4: Individual | D4: 2026-03-25 | E4: 2026-03-31 | F4: 200 | G4: 6.51 | H4: 6.9 | I4: =F4*G4 -> 1302 | J4: =F4*H4 -> 1380 | K4: =I4-J4 -> -78 | L4: =IF(J4<>0,K4/J4,0) -> -0.056521739 | M4: =IF(AND(D4<>"",E4<>""),IF((DATEVALUE(E4)-DATEVALUE(D4))>365,"Long Term","Short Term"),"") -> Short Term
I5: =IF(F5<>"",F5*G5,"") | J5: =IF(F5<>"",F5*H5,"") | K5: =IF(J5<>"",I5-J5,"") | L5: =IF(AND(J5<>"",J5<>0),K5/J5,"") | M5: =IF(AND(D5<>"",E5<>""),IF((DATEVALUE(E5)-DATEVALUE(D5))>365,"Long Term","Short Term"),"")
A6: YTD SUMMARY | I6: =IF(F6<>"",F6*G6,"") | J6: =IF(F6<>"",F6*H6,"") | K6: =IF(J6<>"",I6-J6,"") | L6: =IF(AND(J6<>"",J6<>0),K6/J6,"") | M6: =IF(AND(D6<>"",E6<>""),IF((DATEVALUE(E6)-DATEVALUE(D6))>365,"Long Term","Short Term"),"")
A7: Total Realized G/L | I7: =IF(F7<>"",F7*G7,"") | J7: =IF(F7<>"",F7*H7,"") | K7: =IF(J7<>"",I7-J7,"") | L7: =IF(AND(J7<>"",J7<>0),K7/J7,"") | M7: =IF(AND(D7<>"",E7<>""),IF((DATEVALUE(E7)-DATEVALUE(D7))>365,"Long Term","Short Term"),"")
I8: =IF(F8<>"",F8*G8,"") | J8: =IF(F8<>"",F8*H8,"") | K8: =IF(J8<>"",I8-J8,"") | L8: =IF(AND(J8<>"",J8<>0),K8/J8,"") | M8: =IF(AND(D8<>"",E8<>""),IF((DATEVALUE(E8)-DATEVALUE(D8))>365,"Long Term","Short Term"),"")
I9: =IF(F9<>"",F9*G9,"") | J9: =IF(F9<>"",F9*H9,"") | K9: =IF(J9<>"",I9-J9,"") | L9: =IF(AND(J9<>"",J9<>0),K9/J9,"") | M9: =IF(AND(D9<>"",E9<>""),IF((DATEVALUE(E9)-DATEVALUE(D9))>365,"Long Term","Short Term"),"")
I10: =IF(F10<>"",F10*G10,"") | J10: =IF(F10<>"",F10*H10,"") | K10: =IF(J10<>"",I10-J10,"") | L10: =IF(AND(J10<>"",J10<>0),K10/J10,"") | M10: =IF(AND(D10<>"",E10<>""),IF((DATEVALUE(E10)-DATEVALUE(D10))>365,"Long Term","Short Term"),"")
I11: =IF(F11<>"",F11*G11,"") | J11: =IF(F11<>"",F11*H11,"") | K11: =IF(J11<>"",I11-J11,"") | L11: =IF(AND(J11<>"",J11<>0),K11/J11,"") | M11: =IF(AND(D11<>"",E11<>""),IF((DATEVALUE(E11)-DATEVALUE(D11))>365,"Long Term","Short Term"),"")
I12: =IF(F12<>"",F12*G12,"") | J12: =IF(F12<>"",F12*H12,"") | K12: =IF(J12<>"",I12-J12,"") | L12: =IF(AND(J12<>"",J12<>0),K12/J12,"") | M12: =IF(AND(D12<>"",E12<>""),IF((DATEVALUE(E12)-DATEVALUE(D12))>365,"Long Term","Short Term"),"")
I13: =IF(F13<>"",F13*G13,"") | J13: =IF(F13<>"",F13*H13,"") | K13: =IF(J13<>"",I13-J13,"") | L13: =IF(AND(J13<>"",J13<>0),K13/J13,"") | M13: =IF(AND(D13<>"",E13<>""),IF((DATEVALUE(E13)-DATEVALUE(D13))>365,"Long Term","Short Term"),"")
I14: =IF(F14<>"",F14*G14,"") | J14: =IF(F14<>"",F14*H14,"") | K14: =IF(J14<>"",I14-J14,"") | L14: =IF(AND(J14<>"",J14<>0),K14/J14,"") | M14: =IF(AND(D14<>"",E14<>""),IF((DATEVALUE(E14)-DATEVALUE(D14))>365,"Long Term","Short Term"),"")
I15: =IF(F15<>"",F15*G15,"") | J15: =IF(F15<>"",F15*H15,"") | K15: =IF(J15<>"",I15-J15,"") | L15: =IF(AND(J15<>"",J15<>0),K15/J15,"") | M15: =IF(AND(D15<>"",E15<>""),IF((DATEVALUE(E15)-DATEVALUE(D15))>365,"Long Term","Short Term"),"")
I16: =IF(F16<>"",F16*G16,"") | J16: =IF(F16<>"",F16*H16,"") | K16: =IF(J16<>"",I16-J16,"") | L16: =IF(AND(J16<>"",J16<>0),K16/J16,"") | M16: =IF(AND(D16<>"",E16<>""),IF((DATEVALUE(E16)-DATEVALUE(D16))>365,"Long Term","Short Term"),"")
I17: =IF(F17<>"",F17*G17,"") | J17: =IF(F17<>"",F17*H17,"") | K17: =IF(J17<>"",I17-J17,"") | L17: =IF(AND(J17<>"",J17<>0),K17/J17,"") | M17: =IF(AND(D17<>"",E17<>""),IF((DATEVALUE(E17)-DATEVALUE(D17))>365,"Long Term","Short Term"),"")
I18: =IF(F18<>"",F18*G18,"") | J18: =IF(F18<>"",F18*H18,"") | K18: =IF(J18<>"",I18-J18,"") | L18: =IF(AND(J18<>"",J18<>0),K18/J18,"") | M18: =IF(AND(D18<>"",E18<>""),IF((DATEVALUE(E18)-DATEVALUE(D18))>365,"Long Term","Short Term"),"")
I19: =IF(F19<>"",F19*G19,"") | J19: =IF(F19<>"",F19*H19,"") | K19: =IF(J19<>"",I19-J19,"") | L19: =IF(AND(J19<>"",J19<>0),K19/J19,"") | M19: =IF(AND(D19<>"",E19<>""),IF((DATEVALUE(E19)-DATEVALUE(D19))>365,"Long Term","Short Term"),"")
... I500: =IF(F500<>"",F500*G500,"") | J500: =IF(F500<>"",F500*H500,"") | K500: =IF(J500<>"",I500-J500,"") | L500: =IF(AND(J500<>"",J500<>0),K500/J500,"") | M500: =IF(AND(D500<>"",E500<>""),IF((DATEVALUE(E500)-DATEVALUE(D500))>365,"Long Term","Short Term"),"")

Sheet Watchlist
A1: Symbol | B1: Description | C1: Sector | D1: Current Price | E1: Target Entry | F1: Gap to Entry | G1: Thesis | H1: Catalyst | I1: Priority | J1: Added Date
A2: ARM | B2: ARM Holdings | C2: IT | D2: =IFERROR(__xludf.DUMMYFUNCTION("googlefinance(A2,""price"")"),149.11) -> 149.11 | E2: 120 | F2: =IF(D2<>0,(D2-E2)/D2,0) -> 0.195225 | G2: Semiconductor IP leader. AI chip demand. | H2: Earnings beat | I2: Warm | J2: 2026-03-24
A3: DE | B3: Deere & Co | C3: Industrials | D3: =IFERROR(__xludf.DUMMYFUNCTION("googlefinance(A3,""price"")"),575.71) -> 575.71 | E3: 480 | F3: =IF(D3<>0,(D3-E3)/D3,0) -> 0.1662469 | G3: Ag equipment at cycle trough. | H3: Guidance upgrade | I3: Cold | J3: 2026-04-02
A4: PG | B4: Procter & Gamble | C4: Consumer | D4: =IFERROR(__xludf.DUMMYFUNCTION("googlefinance(A4,""price"")"),143.12) -> 143.12 | E4: 155 | F4: =IF(D4<>0,(D4-E4)/D4,0) -> -0.083007267 | G4: Recession-proof staples. | H4: Market selloff | I4: Warm | J4: 2026-04-01
D5: =IFERROR(__xludf.DUMMYFUNCTION("IF(A5<>"""",googlefinance(A5,""price""),"""")"),"") | F5: =IF(AND(D5<>"",E5<>""),(D5-E5)/D5,"")
D6: =IFERROR(__xludf.DUMMYFUNCTION("IF(A6<>"""",googlefinance(A6,""price""),"""")"),"") | F6: =IF(AND(D6<>"",E6<>""),(D6-E6)/D6,"")
D7: =IFERROR(__xludf.DUMMYFUNCTION("IF(A7<>"""",googlefinance(A7,""price""),"""")"),"") | F7: =IF(AND(D7<>"",E7<>""),(D7-E7)/D7,"")
D8: =IFERROR(__xludf.DUMMYFUNCTION("IF(A8<>"""",googlefinance(A8,""price""),"""")"),"") | F8: =IF(AND(D8<>"",E8<>""),(D8-E8)/D8,"")
D9: =IFERROR(__xludf.DUMMYFUNCTION("IF(A9<>"""",googlefinance(A9,""price""),"""")"),"") | F9: =IF(AND(D9<>"",E9<>""),(D9-E9)/D9,"")
D10: =IFERROR(__xludf.DUMMYFUNCTION("IF(A10<>"""",googlefinance(A10,""price""),"""")"),"") | F10: =IF(AND(D10<>"",E10<>""),(D10-E10)/D10,"")
D11: =IFERROR(__xludf.DUMMYFUNCTION("IF(A11<>"""",googlefinance(A11,""price""),"""")"),"") | F11: =IF(AND(D11<>"",E11<>""),(D11-E11)/D11,"")
D12: =IFERROR(__xludf.DUMMYFUNCTION("IF(A12<>"""",googlefinance(A12,""price""),"""")"),"") | F12: =IF(AND(D12<>"",E12<>""),(D12-E12)/D12,"")
D13: =IFERROR(__xludf.DUMMYFUNCTION("IF(A13<>"""",googlefinance(A13,""price""),"""")"),"") | F13: =IF(AND(D13<>"",E13<>""),(D13-E13)/D13,"")
D14: =IFERROR(__xludf.DUMMYFUNCTION("IF(A14<>"""",googlefinance(A14,""price""),"""")"),"") | F14: =IF(AND(D14<>"",E14<>""),(D14-E14)/D14,"")
D15: =IFERROR(__xludf.DUMMYFUNCTION("IF(A15<>"""",googlefinance(A15,""price""),"""")"),"") | F15: =IF(AND(D15<>"",E15<>""),(D15-E15)/D15,"")
D16: =IFERROR(__xludf.DUMMYFUNCTION("IF(A16<>"""",googlefinance(A16,""price""),"""")"),"") | F16: =IF(AND(D16<>"",E16<>""),(D16-E16)/D16,"")
D17: =IFERROR(__xludf.DUMMYFUNCTION("IF(A17<>"""",googlefinance(A17,""price""),"""")"),"") | F17: =IF(AND(D17<>"",E17<>""),(D17-E17)/D17,"")
D18: =IFERROR(__xludf.DUMMYFUNCTION("IF(A18<>"""",googlefinance(A18,""price""),"""")"),"") | F18: =IF(AND(D18<>"",E18<>""),(D18-E18)/D18,"")
D19: =IFERROR(__xludf.DUMMYFUNCTION("IF(A19<>"""",googlefinance(A19,""price""),"""")"),"") | F19: =IF(AND(D19<>"",E19<>""),(D19-E19)/D19,"")
D20: =IFERROR(__xludf.DUMMYFUNCTION("IF(A20<>"""",googlefinance(A20,""price""),"""")"),"") | F20: =IF(AND(D20<>"",E20<>""),(D20-E20)/D20,"")
D21: =IFERROR(__xludf.DUMMYFUNCTION("IF(A21<>"""",googlefinance(A21,""price""),"""")"),"") | F21: =IF(AND(D21<>"",E21<>""),(D21-E21)/D21,"")
D22: =IFERROR(__xludf.DUMMYFUNCTION("IF(A22<>"""",googlefinance(A22,""price""),"""")"),"") | F22: =IF(AND(D22<>"",E22<>""),(D22-E22)/D22,"")
D23: =IFERROR(__xludf.DUMMYFUNCTION("IF(A23<>"""",googlefinance(A23,""price""),"""")"),"") | F23: =IF(AND(D23<>"",E23<>""),(D23-E23)/D23,"")
D24: =IFERROR(__xludf.DUMMYFUNCTION("IF(A24<>"""",googlefinance(A24,""price""),"""")"),"") | F24: =IF(AND(D24<>"",E24<>""),(D24-E24)/D24,"")
D25: =IFERROR(__xludf.DUMMYFUNCTION("IF(A25<>"""",googlefinance(A25,""price""),"""")"),"") | F25: =IF(AND(D25<>"",E25<>""),(D25-E25)/D25,"")
D26: =IFERROR(__xludf.DUMMYFUNCTION("IF(A26<>"""",googlefinance(A26,""price""),"""")"),"") | F26: =IF(AND(D26<>"",E26<>""),(D26-E26)/D26,"")
D27: =IFERROR(__xludf.DUMMYFUNCTION("IF(A27<>"""",googlefinance(A27,""price""),"""")"),"") | F27: =IF(AND(D27<>"",E27<>""),(D27-E27)/D27,"")
D28: =IFERROR(__xludf.DUMMYFUNCTION("IF(A28<>"""",googlefinance(A28,""price""),"""")"),"") | F28: =IF(AND(D28<>"",E28<>""),(D28-E28)/D28,"")
D29: =IFERROR(__xludf.DUMMYFUNCTION("IF(A29<>"""",googlefinance(A29,""price""),"""")"),"") | F29: =IF(AND(D29<>"",E29<>""),(D29-E29)/D29,"")
D30: =IFERROR(__xludf.DUMMYFUNCTION("IF(A30<>"""",googlefinance(A30,""price""),"""")"),"") | F30: =IF(AND(D30<>"",E30<>""),(D30-E30)/D30,"")
D31: =IFERROR(__xludf.DUMMYFUNCTION("IF(A31<>"""",googlefinance(A31,""price""),"""")"),"") | F31: =IF(AND(D31<>"",E31<>""),(D31-E31)/D31,"")
D32: =IFERROR(__xludf.DUMMYFUNCTION("IF(A32<>"""",googlefinance(A32,""price""),"""")"),"") | F32: =IF(AND(D32<>"",E32<>""),(D32-E32)/D32,"")
D33: =IFERROR(__xludf.DUMMYFUNCTION("IF(A33<>"""",googlefinance(A33,""price""),"""")"),"") | F33: =IF(AND(D33<>"",E33<>""),(D33-E33)/D33,"")
D34: =IFERROR(__xludf.DUMMYFUNCTION("IF(A34<>"""",googlefinance(A34,""price""),"""")"),"") | F34: =IF(AND(D34<>"",E34<>""),(D34-E34)/D34,"")
D35: =IFERROR(__xludf.DUMMYFUNCTION("IF(A35<>"""",googlefinance(A35,""price""),"""")"),"") | F35: =IF(AND(D35<>"",E35<>""),(D35-E35)/D35,"")
D36: =IFERROR(__xludf.DUMMYFUNCTION("IF(A36<>"""",googlefinance(A36,""price""),"""")"),"") | F36: =IF(AND(D36<>"",E36<>""),(D36-E36)/D36,"")
D37: =IFERROR(__xludf.DUMMYFUNCTION("IF(A37<>"""",googlefinance(A37,""price""),"""")"),"") | F37: =IF(AND(D37<>"",E37<>""),(D37-E37)/D37,"")
D38: =IFERROR(__xludf.DUMMYFUNCTION("IF(A38<>"""",googlefinance(A38,""price""),"""")"),"") | F38: =IF(AND(D38<>"",E38<>""),(D38-E38)/D38,"")
D39: =IFERROR(__xludf.DUMMYFUNCTION("IF(A39<>"""",googlefinance(A39,""price""),"""")"),"") | F39: =IF(AND(D39<>"",E39<>""),(D39-E39)/D39,"")
D40: =IFERROR(__xludf.DUMMYFUNCTION("IF(A40<>"""",googlefinance(A40,""price""),"""")"),"") | F40: =IF(AND(D40<>"",E40<>""),(D40-E40)/D40,"")
D41: =IFERROR(__xludf.DUMMYFUNCTION("IF(A41<>"""",googlefinance(A41,""price""),"""")"),"") | F41: =IF(AND(D41<>"",E41<>""),(D41-E41)/D41,"")
D42: =IFERROR(__xludf.DUMMYFUNCTION("IF(A42<>"""",googlefinance(A42,""price""),"""")"),"") | F42: =IF(AND(D42<>"",E42<>""),(D42-E42)/D42,"")
D43: =IFERROR(__xludf.DUMMYFUNCTION("IF(A43<>"""",googlefinance(A43,""price""),"""")"),"") | F43: =IF(AND(D43<>"",E43<>""),(D43-E43)/D43,"")
D44: =IFERROR(__xludf.DUMMYFUNCTION("IF(A44<>"""",googlefinance(A44,""price""),"""")"),"") | F44: =IF(AND(D44<>"",E44<>""),(D44-E44)/D44,"")
D45: =IFERROR(__xludf.DUMMYFUNCTION("IF(A45<>"""",googlefinance(A45,""price""),"""")"),"") | F45: =IF(AND(D45<>"",E45<>""),(D45-E45)/D45,"")
D46: =IFERROR(__xludf.DUMMYFUNCTION("IF(A46<>"""",googlefinance(A46,""price""),"""")"),"") | F46: =IF(AND(D46<>"",E46<>""),(D46-E46)/D46,"")
D47: =IFERROR(__xludf.DUMMYFUNCTION("IF(A47<>"""",googlefinance(A47,""price""),"""")"),"") | F47: =IF(AND(D47<>"",E47<>""),(D47-E47)/D47,"")
D48: =IFERROR(__xludf.DUMMYFUNCTION("IF(A48<>"""",googlefinance(A48,""price""),"""")"),"") | F48: =IF(AND(D48<>"",E48<>""),(D48-E48)/D48,"")
D49: =IFERROR(__xludf.DUMMYFUNCTION("IF(A49<>"""",googlefinance(A49,""price""),"""")"),"") | F49: =IF(AND(D49<>"",E49<>""),(D49-E49)/D49,"")
D50: =IFERROR(__xludf.DUMMYFUNCTION("IF(A50<>"""",googlefinance(A50,""price""),"""")"),"") | F50: =IF(AND(D50<>"",E50<>""),(D50-E50)/D50,"")
D51: =IFERROR(__xludf.DUMMYFUNCTION("IF(A51<>"""",googlefinance(A51,""price""),"""")"),"") | F51: =IF(AND(D51<>"",E51<>""),(D51-E51)/D51,"")
D52: =IFERROR(__xludf.DUMMYFUNCTION("IF(A52<>"""",googlefinance(A52,""price""),"""")"),"") | F52: =IF(AND(D52<>"",E52<>""),(D52-E52)/D52,"")
D53: =IFERROR(__xludf.DUMMYFUNCTION("IF(A53<>"""",googlefinance(A53,""price""),"""")"),"") | F53: =IF(AND(D53<>"",E53<>""),(D53-E53)/D53,"")
D54: =IFERROR(__xludf.DUMMYFUNCTION("IF(A54<>"""",googlefinance(A54,""price""),"""")"),"") | F54: =IF(AND(D54<>"",E54<>""),(D54-E54)/D54,"")
D55: =IFERROR(__xludf.DUMMYFUNCTION("IF(A55<>"""",googlefinance(A55,""price""),"""")"),"") | F55: =IF(AND(D55<>"",E55<>""),(D55-E55)/D55,"")
D56: =IFERROR(__xludf.DUMMYFUNCTION("IF(A56<>"""",googlefinance(A56,""price""),"""")"),"") | F56: =IF(AND(D56<>"",E56<>""),(D56-E56)/D56,"")
D57: =IFERROR(__xludf.DUMMYFUNCTION("IF(A57<>"""",googlefinance(A57,""price""),"""")"),"") | F57: =IF(AND(D57<>"",E57<>""),(D57-E57)/D57,"")
D58: =IFERROR(__xludf.DUMMYFUNCTION("IF(A58<>"""",googlefinance(A58,""price""),"""")"),"") | F58: =IF(AND(D58<>"",E58<>""),(D58-E58)/D58,"")
D59: =IFERROR(__xludf.DUMMYFUNCTION("IF(A59<>"""",googlefinance(A59,""price""),"""")"),"") | F59: =IF(AND(D59<>"",E59<>""),(D59-E59)/D59,"")
D60: =IFERROR(__xludf.DUMMYFUNCTION("IF(A60<>"""",googlefinance(A60,""price""),"""")"),"") | F60: =IF(AND(D60<>"",E60<>""),(D60-E60)/D60,"")
D61: =IFERROR(__xludf.DUMMYFUNCTION("IF(A61<>"""",googlefinance(A61,""price""),"""")"),"") | F61: =IF(AND(D61<>"",E61<>""),(D61-E61)/D61,"")
D62: =IFERROR(__xludf.DUMMYFUNCTION("IF(A62<>"""",googlefinance(A62,""price""),"""")"),"") | F62: =IF(AND(D62<>"",E62<>""),(D62-E62)/D62,"")
D63: =IFERROR(__xludf.DUMMYFUNCTION("IF(A63<>"""",googlefinance(A63,""price""),"""")"),"") | F63: =IF(AND(D63<>"",E63<>""),(D63-E63)/D63,"")
D64: =IFERROR(__xludf.DUMMYFUNCTION("IF(A64<>"""",googlefinance(A64,""price""),"""")"),"") | F64: =IF(AND(D64<>"",E64<>""),(D64-E64)/D64,"")
D65: =IFERROR(__xludf.DUMMYFUNCTION("IF(A65<>"""",googlefinance(A65,""price""),"""")"),"") | F65: =IF(AND(D65<>"",E65<>""),(D65-E65)/D65,"")
D66: =IFERROR(__xludf.DUMMYFUNCTION("IF(A66<>"""",googlefinance(A66,""price""),"""")"),"") | F66: =IF(AND(D66<>"",E66<>""),(D66-E66)/D66,"")
D67: =IFERROR(__xludf.DUMMYFUNCTION("IF(A67<>"""",googlefinance(A67,""price""),"""")"),"") | F67: =IF(AND(D67<>"",E67<>""),(D67-E67)/D67,"")
D68: =IFERROR(__xludf.DUMMYFUNCTION("IF(A68<>"""",googlefinance(A68,""price""),"""")"),"") | F68: =IF(AND(D68<>"",E68<>""),(D68-E68)/D68,"")
D69: =IFERROR(__xludf.DUMMYFUNCTION("IF(A69<>"""",googlefinance(A69,""price""),"""")"),"") | F69: =IF(AND(D69<>"",E69<>""),(D69-E69)/D69,"")
D70: =IFERROR(__xludf.DUMMYFUNCTION("IF(A70<>"""",googlefinance(A70,""price""),"""")"),"") | F70: =IF(AND(D70<>"",E70<>""),(D70-E70)/D70,"")
D71: =IFERROR(__xludf.DUMMYFUNCTION("IF(A71<>"""",googlefinance(A71,""price""),"""")"),"") | F71: =IF(AND(D71<>"",E71<>""),(D71-E71)/D71,"")
D72: =IFERROR(__xludf.DUMMYFUNCTION("IF(A72<>"""",googlefinance(A72,""price""),"""")"),"") | F72: =IF(AND(D72<>"",E72<>""),(D72-E72)/D72,"")
D73: =IFERROR(__xludf.DUMMYFUNCTION("IF(A73<>"""",googlefinance(A73,""price""),"""")"),"") | F73: =IF(AND(D73<>"",E73<>""),(D73-E73)/D73,"")
D74: =IFERROR(__xludf.DUMMYFUNCTION("IF(A74<>"""",googlefinance(A74,""price""),"""")"),"") | F74: =IF(AND(D74<>"",E74<>""),(D74-E74)/D74,"")
D75: =IFERROR(__xludf.DUMMYFUNCTION("IF(A75<>"""",googlefinance(A75,""price""),"""")"),"") | F75: =IF(AND(D75<>"",E75<>""),(D75-E75)/D75,"")
D76: =IFERROR(__xludf.DUMMYFUNCTION("IF(A76<>"""",googlefinance(A76,""price""),"""")"),"") | F76: =IF(AND(D76<>"",E76<>""),(D76-E76)/D76,"")
D77: =IFERROR(__xludf.DUMMYFUNCTION("IF(A77<>"""",googlefinance(A77,""price""),"""")"),"") | F77: =IF(AND(D77<>"",E77<>""),(D77-E77)/D77,"")
D78: =IFERROR(__xludf.DUMMYFUNCTION("IF(A78<>"""",googlefinance(A78,""price""),"""")"),"") | F78: =IF(AND(D78<>"",E78<>""),(D78-E78)/D78,"")
D79: =IFERROR(__xludf.DUMMYFUNCTION("IF(A79<>"""",googlefinance(A79,""price""),"""")"),"") | F79: =IF(AND(D79<>"",E79<>""),(D79-E79)/D79,"")
D80: =IFERROR(__xludf.DUMMYFUNCTION("IF(A80<>"""",googlefinance(A80,""price""),"""")"),"") | F80: =IF(AND(D80<>"",E80<>""),(D80-E80)/D80,"")
D81: =IFERROR(__xludf.DUMMYFUNCTION("IF(A81<>"""",googlefinance(A81,""price""),"""")"),"") | F81: =IF(AND(D81<>"",E81<>""),(D81-E81)/D81,"")
D82: =IFERROR(__xludf.DUMMYFUNCTION("IF(A82<>"""",googlefinance(A82,""price""),"""")"),"") | F82: =IF(AND(D82<>"",E82<>""),(D82-E82)/D82,"")
D83: =IFERROR(__xludf.DUMMYFUNCTION("IF(A83<>"""",googlefinance(A83,""price""),"""")"),"") | F83: =IF(AND(D83<>"",E83<>""),(D83-E83)/D83,"")
D84: =IFERROR(__xludf.DUMMYFUNCTION("IF(A84<>"""",googlefinance(A84,""price""),"""")"),"") | F84: =IF(AND(D84<>"",E84<>""),(D84-E84)/D84,"")
D85: =IFERROR(__xludf.DUMMYFUNCTION("IF(A85<>"""",googlefinance(A85,""price""),"""")"),"") | F85: =IF(AND(D85<>"",E85<>""),(D85-E85)/D85,"")
D86: =IFERROR(__xludf.DUMMYFUNCTION("IF(A86<>"""",googlefinance(A86,""price""),"""")"),"") | F86: =IF(AND(D86<>"",E86<>""),(D86-E86)/D86,"")
D87: =IFERROR(__xludf.DUMMYFUNCTION("IF(A87<>"""",googlefinance(A87,""price""),"""")"),"") | F87: =IF(AND(D87<>"",E87<>""),(D87-E87)/D87,"")
D88: =IFERROR(__xludf.DUMMYFUNCTION("IF(A88<>"""",googlefinance(A88,""price""),"""")"),"") | F88: =IF(AND(D88<>"",E88<>""),(D88-E88)/D88,"")
D89: =IFERROR(__xludf.DUMMYFUNCTION("IF(A89<>"""",googlefinance(A89,""price""),"""")"),"") | F89: =IF(AND(D89<>"",E89<>""),(D89-E89)/D89,"")
D90: =IFERROR(__xludf.DUMMYFUNCTION("IF(A90<>"""",googlefinance(A90,""price""),"""")"),"") | F90: =IF(AND(D90<>"",E90<>""),(D90-E90)/D90,"")
D91: =IFERROR(__xludf.DUMMYFUNCTION("IF(A91<>"""",googlefinance(A91,""price""),"""")"),"") | F91: =IF(AND(D91<>"",E91<>""),(D91-E91)/D91,"")
D92: =IFERROR(__xludf.DUMMYFUNCTION("IF(A92<>"""",googlefinance(A92,""price""),"""")"),"") | F92: =IF(AND(D92<>"",E92<>""),(D92-E92)/D92,"")
D93: =IFERROR(__xludf.DUMMYFUNCTION("IF(A93<>"""",googlefinance(A93,""price""),"""")"),"") | F93: =IF(AND(D93<>"",E93<>""),(D93-E93)/D93,"")
D94: =IFERROR(__xludf.DUMMYFUNCTION("IF(A94<>"""",googlefinance(A94,""price""),"""")"),"") | F94: =IF(AND(D94<>"",E94<>""),(D94-E94)/D94,"")
D95: =IFERROR(__xludf.DUMMYFUNCTION("IF(A95<>"""",googlefinance(A95,""price""),"""")"),"") | F95: =IF(AND(D95<>"",E95<>""),(D95-E95)/D95,"")
D96: =IFERROR(__xludf.DUMMYFUNCTION("IF(A96<>"""",googlefinance(A96,""price""),"""")"),"") | F96: =IF(AND(D96<>"",E96<>""),(D96-E96)/D96,"")
D97: =IFERROR(__xludf.DUMMYFUNCTION("IF(A97<>"""",googlefinance(A97,""price""),"""")"),"") | F97: =IF(AND(D97<>"",E97<>""),(D97-E97)/D97,"")
D98: =IFERROR(__xludf.DUMMYFUNCTION("IF(A98<>"""",googlefinance(A98,""price""),"""")"),"") | F98: =IF(AND(D98<>"",E98<>""),(D98-E98)/D98,"")
D99: =IFERROR(__xludf.DUMMYFUNCTION("IF(A99<>"""",googlefinance(A99,""price""),"""")"),"") | F99: =IF(AND(D99<>"",E99<>""),(D99-E99)/D99,"")
D100: =IFERROR(__xludf.DUMMYFUNCTION("IF(A100<>"""",googlefinance(A100,""price""),"""")"),"") | F100: =IF(AND(D100<>"",E100<>""),(D100-E100)/D100,"")

Sheet Trade Journal
A1: Date | B1: Market View | C1: Symbols | D1: Decision | E1: Outcome | F1: Lesson
A2: 2026-04-01 | B2: Cautious | C2: LITE, CF, NTR | D2: Trimmed LITE. Rotated into fertilizer basket. | E2: Locked in gains. | F2: Take profits mechanically.
A3: 2026-04-02 | B3: Cautious | C3: GNK, NAT, FJET | D3: Added GNK with tiered OCO. Doubled NAT. | E3: All green day one. | F3: Momentum + defined exits work.

Sheet Dividend Tracker
A1: Symbol | B1: Pay Date | C1: Amount/Share | D1: Shares Held | E1: Total Payment | F1: Account | G1: Reinvested?
A2: NAT | B2: 2026-03-24 | C2: 0.12 | D2: 400 | E2: =C2*D2 -> 48 | F2: No
A3: ENB | B3: 2026-03-01 | C3: 0.915 | D3: 25 | E3: =C3*D3 -> 22.875 | F3: No
E4: =IF(C4<>"",C4*D4,"")
A5: YTD TOTAL | E5: =IF(C5<>"",C5*D5,"")
E6: =IF(C6<>"",C6*D6,"")
E7: =IF(C7<>"",C7*D7,"")
E8: =IF(C8<>"",C8*D8,"")
E9: =IF(C9<>"",C9*D9,"")
E10: =IF(C10<>"",C10*D10,"")
E11: =IF(C11<>"",C11*D11,"")
E12: =IF(C12<>"",C12*D12,"")
E13: =IF(C13<>"",C13*D13,"")
E14: =IF(C14<>"",C14*D14,"")
E15: =IF(C15<>"",C15*D15,"")
E16: =IF(C16<>"",C16*D16,"")
E17: =IF(C17<>"",C17*D17,"")
... E500: =IF(C500<>"",C500*D500,"")

Sheet How To Use
A1: ACTIVE TRADER PORTFOLIO TRACKER — SETUP GUIDE
A3: STEP 1: MAKE YOUR OWN COPY
A4: Google Sheets: File > Make a Copy. Excel: Save As.
A6: STEP 2: AUTO-PRICING IS ALREADY SET UP
A7: Column H (Current Price) in Positions and Column D in Watchlist use =GOOGLEFINANCE() automatically.
A8: Prices update every ~20 min for free. Only works in Google Sheets — not Excel or LibreOffice.
A10: STEP 3: ADD YOUR POSITIONS
A11: Delete sample data. Add: Symbol, Description, Account, Sector, Quantity, Avg Cost/Share.
A12: Market Value, Cost Basis, Gain/Loss auto-calculate. Use dropdowns for Account/Sector/Status.
A14: STEP 4: LOG TRADES
A15: Add closed positions to Realized Trades. Term auto-calculates (Short/Long based on hold time).
A17: STEP 5: WATCHLIST
... A31: Built by an active trader managing a six-figure portfolio across multiple accounts.
